<?xml version="1.0" encoding="utf-8"?>
<Race xmlns:xsd="http://www.w3.org/2001/XMLSchema" xmlns:xsi="http://www.w3.org/2001/XMLSchema-instance">
  <Checkpoints>
    <Vector3>
      <X>700.2298</X>
      <Y>-2057.57275</Y>
      <Z>28.47602</Z>
    </Vector3>
    <Vector3>
      <X>659.3732</X>
      <Y>-2054.001</Y>
      <Z>28.4684925</Z>
    </Vector3>
    <Vector3>
      <X>616.386353</X>
      <Y>-2049.93848</Y>
      <Z>39.49846</Z>
    </Vector3>
    <Vector3>
      <X>570.3133</X>
      <Y>-2047.30835</Y>
      <Z>42.4152069</Z>
    </Vector3>
    <Vector3>
      <X>500.394073</X>
      <Y>-2045.49976</Y>
      <Z>45.2461472</Z>
    </Vector3>
    <Vector3>
      <X>456.24295</X>
      <Y>-2065.474</Y>
      <Z>48.46958</Z>
    </Vector3>
    <Vector3>
      <X>388.2229</X>
      <Y>-2096.82227</Y>
      <Z>52.4299049</Z>
    </Vector3>
    <Vector3>
      <X>349.2959</X>
      <Y>-2119.72266</Y>
      <Z>54.8064651</Z>
    </Vector3>
    <Vector3>
      <X>276.4679</X>
      <Y>-2168.074</Y>
      <Z>53.218792</Z>
    </Vector3>
    <Vector3>
      <X>258.079437</X>
      <Y>-2245.5354</Y>
      <Z>33.65148</Z>
    </Vector3>
    <Vector3>
      <X>246.322113</X>
      <Y>-2265.518</Y>
      <Z>35.8834</Z>
    </Vector3>
    <Vector3>
      <X>222.47934</X>
      <Y>-2312.18848</Y>
      <Z>33.7732162</Z>
    </Vector3>
    <Vector3>
      <X>106.174</X>
      <Y>-2320.489</Y>
      <Z>34.08318</Z>
    </Vector3>
    <Vector3>
      <X>-116.942627</X>
      <Y>-2340.29834</Y>
      <Z>32.5004234</Z>
    </Vector3>
    <Vector3>
      <X>-360.976959</X>
      <Y>-2361.95947</Y>
      <Z>30.7689972</Z>
    </Vector3>
    <Vector3>
      <X>-460.666321</X>
      <Y>-2358.68213</Y>
      <Z>46.228</Z>
    </Vector3>
    <Vector3>
      <X>-488.448425</X>
      <Y>-2300.006</Y>
      <Z>66.82201</Z>
    </Vector3>
    <Vector3>
      <X>-549.2521</X>
      <Y>-2229.60718</Y>
      <Z>72.94904</Z>
    </Vector3>
    <Vector3>
      <X>-631.263733</X>
      <Y>-2173.51465</Y>
      <Z>75.11747</Z>
    </Vector3>
    <Vector3>
      <X>-710.2818</X>
      <Y>-2114.5354</Y>
      <Z>66.26601</Z>
    </Vector3>
    <Vector3>
      <X>-824.8131</X>
      <Y>-2002.70947</Y>
      <Z>55.25243</Z>
    </Vector3>
    <Vector3>
      <X>-858.1375</X>
      <Y>-1970.19922</Y>
      <Z>61.5632477</Z>
    </Vector3>
    <Vector3>
      <X>-893.2509</X>
      <Y>-1758.3009</Y>
      <Z>69.78931</Z>
    </Vector3>
    <Vector3>
      <X>-906.683533</X>
      <Y>-1711.2804</Y>
      <Z>72.4908752</Z>
    </Vector3>
    <Vector3>
      <X>-976.0819</X>
      <Y>-1649.7782</Y>
      <Z>75.67199</Z>
    </Vector3>
    <Vector3>
      <X>-1018.79071</X>
      <Y>-1618.44629</Y>
      <Z>77.4819946</Z>
    </Vector3>
    <Vector3>
      <X>-1061.49817</X>
      <Y>-1587.1134</Y>
      <Z>79.29187</Z>
    </Vector3>
    <Vector3>
      <X>-1117.09827</X>
      <Y>-1546.32056</Y>
      <Z>81.64858</Z>
    </Vector3>
    <Vector3>
      <X>-1186.397</X>
      <Y>-1495.47852</Y>
      <Z>84.58683</Z>
    </Vector3>
    <Vector3>
      <X>-1204.79419</X>
      <Y>-1440.827</Y>
      <Z>58.81556</Z>
    </Vector3>
    <Vector3>
      <X>-1241.74585</X>
      <Y>-1331.49109</Y>
      <Z>19.2506485</Z>
    </Vector3>
    <Vector3>
      <X>-1258.06763</X>
      <Y>-1284.11951</Y>
      <Z>2.96244812</Z>
    </Vector3>
    <Vector3>
      <X>-1292.56592</X>
      <Y>-1198.14429</Y>
      <Z>3.94715977</Z>
    </Vector3>
    <Vector3>
      <X>-1302.64551</X>
      <Y>-1125.1344</Y>
      <Z>5.45041847</Z>
    </Vector3>
    <Vector3>
      <X>-1316.7135</X>
      <Y>-1075.05566</Y>
      <Z>5.95739841</Z>
    </Vector3>
    <Vector3>
      <X>-1338.97266</X>
      <Y>-1032.32</Y>
      <Z>6.855196</Z>
    </Vector3>
    <Vector3>
      <X>-1436.65039</X>
      <Y>-897.8941</Y>
      <Z>10.0164022</Z>
    </Vector3>
    <Vector3>
      <X>-1548.36743</X>
      <Y>-854.176453</Y>
      <Z>9.070312</Z>
    </Vector3>
    <Vector3>
      <X>-1572.05969</X>
      <Y>-863.8516</Y>
      <Z>9.155459</Z>
    </Vector3>
    <Vector3>
      <X>-1624.28955</X>
      <Y>-897.278931</Y>
      <Z>8.003525</Z>
    </Vector3>
    <Vector3>
      <X>-1658.79041</X>
      <Y>-909.1888</Y>
      <Z>7.448352</Z>
    </Vector3>
  </Checkpoints>
  <SpawnPoints>
    <SpawnPoint>
      <Position>
        <X>745.172</X>
        <Y>-2067.648</Y>
        <Z>28.6217613</Z>
      </Position>
      <Heading>85.5230942</Heading>
    </SpawnPoint>
    <SpawnPoint>
      <Position>
        <X>745.9839</X>
        <Y>-2056.332</Y>
        <Z>28.9508152</Z>
      </Position>
      <Heading>89.44771</Heading>
    </SpawnPoint>
    <SpawnPoint>
      <Position>
        <X>744.225</X>
        <Y>-2051.116</Y>
        <Z>28.7137928</Z>
      </Position>
      <Heading>89.0705643</Heading>
    </SpawnPoint>
    <SpawnPoint>
      <Position>
        <X>745.561951</X>
        <Y>-2073.30835</Y>
        <Z>28.7172451</Z>
      </Position>
      <Heading>87.29189</Heading>
    </SpawnPoint>
    <SpawnPoint>
      <Position>
        <X>745.9571</X>
        <Y>-2063.49585</Y>
        <Z>29.0106525</Z>
      </Position>
      <Heading>89.49023</Heading>
    </SpawnPoint>
  </SpawnPoints>
  <AvailableVehicles>
    <VehicleHash>Deluxo</VehicleHash>
    <VehicleHash>Deluxo</VehicleHash>
    <VehicleHash>Deluxo</VehicleHash>
    <VehicleHash>Deluxo</VehicleHash>
    <VehicleHash>Deluxo</VehicleHash>
  </AvailableVehicles>
  <LapsAvailable>false</LapsAvailable>
  <DecorativeProps />
  <Trigger>
    <X>745.8041</X>
    <Y>-2078.80225</Y>
    <Z>28.27301</Z>
  </Trigger>
  <Name>Deluxo 2</Name>
  <Description>We need to keep trying the deluxo fly</Description>
</Race>