<?xml version="1.0" encoding="utf-8"?>
<Race xmlns:xsd="http://www.w3.org/2001/XMLSchema" xmlns:xsi="http://www.w3.org/2001/XMLSchema-instance">
	<Checkpoints>
		<Vector3>
			<X>-3007.350</X>
			<Y>641.467</Y>
			<Z>20.355</Z>
		</Vector3>
		<Vector3>
			<X>-2992.906</X>
			<Y>395.621</Y>
			<Z>13.869</Z>
		</Vector3>
		<Vector3>
			<X>-3026.613</X>
			<Y>177.430</Y>
			<Z>14.859</Z>
		</Vector3>
		<Vector3>
			<X>-2723.381</X>
			<Y>-6.674</Y>
			<Z>14.566</Z>
		</Vector3>
		<Vector3>
			<X>-2567.415</X>
			<Y>-168.320</Y>
			<Z>19.637</Z>
		</Vector3>
		<Vector3>
			<X>-2320.960</X>
			<Y>-312.133</Y>
			<Z>12.845</Z>
		</Vector3>
		<Vector3>
			<X>-2123.094</X>
			<Y>-372.124</Y>
			<Z>12.042</Z>
		</Vector3>
		<Vector3>
			<X>-2006.158</X>
			<Y>-388.157</Y>
			<Z>10.365</Z>
		</Vector3>
		<Vector3>
			<X>-1882.688</X>
			<Y>-470.098</Y>
			<Z>23.241</Z>
		</Vector3>
		<Vector3>
			<X>-1729.319</X>
			<Y>-562.864</Y>
			<Z>36.506</Z>
		</Vector3>
		<Vector3>
			<X>-1747.028</X>
			<Y>-471.332</Y>
			<Z>39.746</Z>
		</Vector3>
		<Vector3>
			<X>-1618.366</X>
			<Y>-308.035</Y>
			<Z>50.501</Z>
		</Vector3>
		<Vector3>
			<X>-1577.095</X>
			<Y>-189.323</Y>
			<Z>54.598</Z>
		</Vector3>
		<Vector3>
			<X>-1647.687</X>
			<Y>-39.206</Y>
			<Z>59.119</Z>
		</Vector3>
		<Vector3>
			<X>-1763.392</X>
			<Y>70.497</Y>
			<Z>67.412</Z>
		</Vector3>
		<Vector3>
			<X>-1909.850</X>
			<Y>190.671</Y>
			<Z>82.727</Z>
		</Vector3>
		<Vector3>
			<X>-1965.248</X>
			<Y>342.650</Y>
			<Z>89.483</Z>
		</Vector3>
		<Vector3>
			<X>-1985.542</X>
			<Y>487.684</Y>
			<Z>103.915</Z>
		</Vector3>
		<Vector3>
			<X>-1925.206</X>
			<Y>668.293</Y>
			<Z>124.330</Z>
		</Vector3>
		<Vector3>
			<X>-1753.594</X>
			<Y>814.990</Y>
			<Z>140.542</Z>
		</Vector3>
		<Vector3>
			<X>-1863.978</X>
			<Y>787.022</Y>
			<Z>139.240</Z>
		</Vector3>
		<Vector3>
			<X>-1993.350</X>
			<Y>699.753</Y>
			<Z>142.244</Z>
		</Vector3>
		<Vector3>
			<X>-2021.677</X>
			<Y>802.887</Y>
			<Z>159.307</Z>
		</Vector3>
		<Vector3>
			<X>-2026.502</X>
			<Y>926.590</Y>
			<Z>176.642</Z>
		</Vector3>
		<Vector3>
			<X>-2134.224</X>
			<Y>972.515</Y>
			<Z>184.300</Z>
		</Vector3>
		<Vector3>
			<X>-2236.042</X>
			<Y>1075.795</Y>
			<Z>196.538</Z>
		</Vector3>
		<Vector3>
			<X>-2315.584</X>
			<Y>1026.210</Y>
			<Z>194.289</Z>
		</Vector3>
		<Vector3>
			<X>-2435.846</X>
			<Y>1037.584</Y>
			<Z>193.645</Z>
		</Vector3>
		<Vector3>
			<X>-2601.960</X>
			<Y>1092.132</Y>
			<Z>168.199</Z>
		</Vector3>
		<Vector3>
			<X>-2632.736</X>
			<Y>1279.174</Y>
			<Z>146.946</Z>
		</Vector3>
		<Vector3>
			<X>-2642.355</X>
			<Y>1490.412</Y>
			<Z>120.415</Z>
		</Vector3>
		<Vector3>
			<X>-2721.123</X>
			<Y>1469.594</Y>
			<Z>99.061</Z>
		</Vector3>
		<Vector3>
			<X>-2755.814</X>
			<Y>1368.505</Y>
			<Z>82.613</Z>
		</Vector3>
		<Vector3>
			<X>-2829.234</X>
			<Y>1287.565</Y>
			<Z>64.883</Z>
		</Vector3>
		<Vector3>
			<X>-2919.690</X>
			<Y>1332.541</Y>
			<Z>44.887</Z>
		</Vector3>
		<Vector3>
			<X>-2998.879</X>
			<Y>1305.884</Y>
			<Z>33.347</Z>
		</Vector3>
		<Vector3>
			<X>-3042.991</X>
			<Y>1211.216</Y>
			<Z>23.217</Z>
		</Vector3>
		<Vector3>
			<X>-3098.106</X>
			<Y>1172.316</Y>
			<Z>19.375</Z>
		</Vector3>
		<Vector3>
			<X>-3123.790</X>
			<Y>1054.625</Y>
			<Z>19.166</Z>
		</Vector3>
		<Vector3>
			<X>-3154.670</X>
			<Y>905.274</Y>
			<Z>13.469</Z>
		</Vector3>
		<Vector3>
			<X>-3081.954</X>
			<Y>771.077</Y>
			<Z>19.112</Z>
		</Vector3>
	</Checkpoints>
	<SpawnPoints>
		<SpawnPoint>
			<Position>
				<X>-3078.951</X>
				<Y>778.613</Y>
				<Z>18.947</Z>
			</Position>
			<Heading>214.580</Heading>
		</SpawnPoint>
		<SpawnPoint>
			<Position>
				<X>-3086.361</X>
				<Y>773.505</Y>
				<Z>18.904</Z>
			</Position>
			<Heading>214.580</Heading>
		</SpawnPoint>
		<SpawnPoint>
			<Position>
				<X>-3087.225</X>
				<Y>782.687</Y>
				<Z>18.533</Z>
			</Position>
			<Heading>214.580</Heading>
		</SpawnPoint>
		<SpawnPoint>
			<Position>
				<X>-3094.635</X>
				<Y>777.579</Y>
				<Z>18.506</Z>
			</Position>
			<Heading>214.580</Heading>
		</SpawnPoint>
		<SpawnPoint>
			<Position>
				<X>-3088.089</X>
				<Y>791.869</Y>
				<Z>18.178</Z>
			</Position>
			<Heading>214.580</Heading>
		</SpawnPoint>
		<SpawnPoint>
			<Position>
				<X>-3095.499</X>
				<Y>786.761</Y>
				<Z>18.144</Z>
			</Position>
			<Heading>214.580</Heading>
		</SpawnPoint>
		<SpawnPoint>
			<Position>
				<X>-3096.362</X>
				<Y>795.943</Y>
				<Z>17.774</Z>
			</Position>
			<Heading>214.580</Heading>
		</SpawnPoint>
		<SpawnPoint>
			<Position>
				<X>-3103.772</X>
				<Y>790.834</Y>
				<Z>17.742</Z>
			</Position>
			<Heading>214.580</Heading>
		</SpawnPoint>
		<SpawnPoint>
			<Position>
				<X>-3097.226</X>
				<Y>805.124</Y>
				<Z>17.405</Z>
			</Position>
			<Heading>214.580</Heading>
		</SpawnPoint>
		<SpawnPoint>
			<Position>
				<X>-3104.636</X>
				<Y>800.016</Y>
				<Z>17.381</Z>
			</Position>
			<Heading>214.580</Heading>
		</SpawnPoint>
		<SpawnPoint>
			<Position>
				<X>-3105.500</X>
				<Y>809.198</Y>
				<Z>17.015</Z>
			</Position>
			<Heading>214.580</Heading>
		</SpawnPoint>
		<SpawnPoint>
			<Position>
				<X>-3112.910</X>
				<Y>804.090</Y>
				<Z>16.995</Z>
			</Position>
			<Heading>214.580</Heading>
		</SpawnPoint>
		<SpawnPoint>
			<Position>
				<X>-3106.364</X>
				<Y>818.380</Y>
				<Z>16.648</Z>
			</Position>
			<Heading>214.580</Heading>
		</SpawnPoint>
		<SpawnPoint>
			<Position>
				<X>-3113.774</X>
				<Y>813.272</Y>
				<Z>16.640</Z>
			</Position>
			<Heading>214.580</Heading>
		</SpawnPoint>
		<SpawnPoint>
			<Position>
				<X>-3114.638</X>
				<Y>822.454</Y>
				<Z>16.275</Z>
			</Position>
			<Heading>214.580</Heading>
		</SpawnPoint>
		<SpawnPoint>
			<Position>
				<X>-3122.048</X>
				<Y>817.346</Y>
				<Z>16.281</Z>
			</Position>
			<Heading>214.580</Heading>
		</SpawnPoint>
		<SpawnPoint>
			<Position>
				<X>-3115.502</X>
				<Y>831.636</Y>
				<Z>15.925</Z>
			</Position>
			<Heading>214.580</Heading>
		</SpawnPoint>
		<SpawnPoint>
			<Position>
				<X>-3122.912</X>
				<Y>826.528</Y>
				<Z>15.939</Z>
			</Position>
			<Heading>214.580</Heading>
		</SpawnPoint>
		<SpawnPoint>
			<Position>
				<X>-3123.776</X>
				<Y>835.709</Y>
				<Z>15.572</Z>
			</Position>
			<Heading>214.580</Heading>
		</SpawnPoint>
		<SpawnPoint>
			<Position>
				<X>-3131.186</X>
				<Y>830.601</Y>
				<Z>15.622</Z>
			</Position>
			<Heading>214.580</Heading>
		</SpawnPoint>
		<SpawnPoint>
			<Position>
				<X>-3124.639</X>
				<Y>844.891</Y>
				<Z>15.260</Z>
			</Position>
			<Heading>214.580</Heading>
		</SpawnPoint>
		<SpawnPoint>
			<Position>
				<X>-3132.049</X>
				<Y>839.783</Y>
				<Z>15.280</Z>
			</Position>
			<Heading>214.580</Heading>
		</SpawnPoint>
		<SpawnPoint>
			<Position>
				<X>-3132.913</X>
				<Y>848.965</Y>
				<Z>14.967</Z>
			</Position>
			<Heading>214.580</Heading>
		</SpawnPoint>
		<SpawnPoint>
			<Position>
				<X>-3140.323</X>
				<Y>843.857</Y>
				<Z>15.030</Z>
			</Position>
			<Heading>214.580</Heading>
		</SpawnPoint>
		<SpawnPoint>
			<Position>
				<X>-3133.777</X>
				<Y>858.147</Y>
				<Z>14.654</Z>
			</Position>
			<Heading>214.580</Heading>
		</SpawnPoint>
		<SpawnPoint>
			<Position>
				<X>-3141.187</X>
				<Y>853.039</Y>
				<Z>14.698</Z>
			</Position>
			<Heading>214.580</Heading>
		</SpawnPoint>
		<SpawnPoint>
			<Position>
				<X>-3142.051</X>
				<Y>862.221</Y>
				<Z>14.424</Z>
			</Position>
			<Heading>214.580</Heading>
		</SpawnPoint>
		<SpawnPoint>
			<Position>
				<X>-3149.461</X>
				<Y>857.113</Y>
				<Z>14.502</Z>
			</Position>
			<Heading>214.580</Heading>
		</SpawnPoint>
		<SpawnPoint>
			<Position>
				<X>-3142.915</X>
				<Y>871.403</Y>
				<Z>14.162</Z>
			</Position>
			<Heading>214.580</Heading>
		</SpawnPoint>
		<SpawnPoint>
			<Position>
				<X>-3150.325</X>
				<Y>866.295</Y>
				<Z>14.247</Z>
			</Position>
			<Heading>214.580</Heading>
		</SpawnPoint>
	</SpawnPoints>
	<AvailableVehicles>
		<VehicleHash>Sultan3</VehicleHash>
		<VehicleHash>Sultan2</VehicleHash>
		<VehicleHash>Sanchez2</VehicleHash>
		<VehicleHash>Manchez2</VehicleHash>
		<VehicleHash>Brawler</VehicleHash>
		<VehicleHash>Hellion</VehicleHash>
	</AvailableVehicles>
	<LapsAvailable>false</LapsAvailable>
	<DecorativeProps>
		<SavedProp>
			<Position>
				<X>-3116.036</X>
				<Y>789.132</Y>
				<Z>17.654</Z>
			</Position>
			<Rotation>
				<X>0.000</X>
				<Y>0.000</Y>
				<Z>-56.000</Z>
			</Rotation>
			<Hash>812376260</Hash>
			<Dynamic>false</Dynamic>
		</SavedProp>
		<SavedProp>
			<Position>
				<X>-2017.276</X>
				<Y>-396.956</Y>
				<Z>10.281</Z>
			</Position>
			<Rotation>
				<X>0.000</X>
				<Y>0.000</Y>
				<Z>-28.800</Z>
			</Rotation>
			<Hash>812376260</Hash>
			<Dynamic>false</Dynamic>
		</SavedProp>
		<SavedProp>
			<Position>
				<X>-1732.974</X>
				<Y>-551.460</Y>
				<Z>36.572</Z>
			</Position>
			<Rotation>
				<X>0.000</X>
				<Y>0.000</Y>
				<Z>180.000</Z>
			</Rotation>
			<Hash>812376260</Hash>
			<Dynamic>false</Dynamic>
		</SavedProp>
		<SavedProp>
			<Position>
				<X>-1607.661</X>
				<Y>-309.936</Y>
				<Z>50.099</Z>
			</Position>
			<Rotation>
				<X>-0.266</X>
				<Y>6.161</Y>
				<Z>-55.986</Z>
			</Rotation>
			<Hash>812376260</Hash>
			<Dynamic>false</Dynamic>
		</SavedProp>
		<SavedProp>
			<Position>
				<X>-1592.669</X>
				<Y>-183.815</Y>
				<Z>54.665</Z>
			</Position>
			<Rotation>
				<X>0.000</X>
				<Y>0.000</Y>
				<Z>-0.801</Z>
			</Rotation>
			<Hash>812376260</Hash>
			<Dynamic>false</Dynamic>
		</SavedProp>
		<SavedProp>
			<Position>
				<X>-1889.727</X>
				<Y>149.907</Y>
				<Z>80.242</Z>
			</Position>
			<Rotation>
				<X>1.086</X>
				<Y>3.736</Y>
				<Z>-60.436</Z>
			</Rotation>
			<Hash>812376260</Hash>
			<Dynamic>false</Dynamic>
		</SavedProp>
		<SavedProp>
			<Position>
				<X>-1765.289</X>
				<Y>812.397</Y>
				<Z>140.024</Z>
			</Position>
			<Rotation>
				<X>1.821</X>
				<Y>-5.559</Y>
				<Z>55.688</Z>
			</Rotation>
			<Hash>812376260</Hash>
			<Dynamic>false</Dynamic>
		</SavedProp>
		<SavedProp>
			<Position>
				<X>-2494.166</X>
				<Y>1041.061</Y>
				<Z>187.796</Z>
			</Position>
			<Rotation>
				<X>-3.530</X>
				<Y>-8.589</Y>
				<Z>36.534</Z>
			</Rotation>
			<Hash>812376260</Hash>
			<Dynamic>false</Dynamic>
		</SavedProp>
		<SavedProp>
			<Position>
				<X>-2644.129</X>
				<Y>1474.260</Y>
				<Z>123.383</Z>
			</Position>
			<Rotation>
				<X>-10.280</X>
				<Y>5.955</Y>
				<Z>37.335</Z>
			</Rotation>
			<Hash>812376260</Hash>
			<Dynamic>false</Dynamic>
		</SavedProp>
		<SavedProp>
			<Position>
				<X>-2662.101</X>
				<Y>1512.698</Y>
				<Z>114.597</Z>
			</Position>
			<Rotation>
				<X>4.310</X>
				<Y>10.399</Y>
				<Z>167.206</Z>
			</Rotation>
			<Hash>812376260</Hash>
			<Dynamic>false</Dynamic>
		</SavedProp>
		<SavedProp>
			<Position>
				<X>-2702.331</X>
				<Y>1510.083</Y>
				<Z>107.585</Z>
			</Position>
			<Rotation>
				<X>-5.086</X>
				<Y>9.255</Y>
				<Z>168.010</Z>
			</Rotation>
			<Hash>812376260</Hash>
			<Dynamic>false</Dynamic>
		</SavedProp>
		<SavedProp>
			<Position>
				<X>-2752.755</X>
				<Y>1358.461</Y>
				<Z>81.601</Z>
			</Position>
			<Rotation>
				<X>-6.720</X>
				<Y>3.920</Y>
				<Z>167.828</Z>
			</Rotation>
			<Hash>812376260</Hash>
			<Dynamic>false</Dynamic>
		</SavedProp>
		<SavedProp>
			<Position>
				<X>-2996.326</X>
				<Y>1319.776</Y>
				<Z>34.645</Z>
			</Position>
			<Rotation>
				<X>-7.350</X>
				<Y>5.554</Y>
				<Z>123.555</Z>
			</Rotation>
			<Hash>812376260</Hash>
			<Dynamic>false</Dynamic>
		</SavedProp>
		<SavedProp>
			<Position>
				<X>-1735.732</X>
				<Y>-569.774</Y>
				<Z>36.453</Z>
			</Position>
			<Rotation>
				<X>0.000</X>
				<Y>0.000</Y>
				<Z>175.999</Z>
			</Rotation>
			<Hash>631705629</Hash>
			<Dynamic>false</Dynamic>
		</SavedProp>
		<SavedProp>
			<Position>
				<X>-1728.958</X>
				<Y>-569.610</Y>
				<Z>36.455</Z>
			</Position>
			<Rotation>
				<X>0.000</X>
				<Y>0.000</Y>
				<Z>-172.801</Z>
			</Rotation>
			<Hash>631705629</Hash>
			<Dynamic>false</Dynamic>
		</SavedProp>
		<SavedProp>
			<Position>
				<X>-1722.288</X>
				<Y>-567.984</Y>
				<Z>36.376</Z>
			</Position>
			<Rotation>
				<X>0.000</X>
				<Y>0.000</Y>
				<Z>-158.401</Z>
			</Rotation>
			<Hash>631705629</Hash>
			<Dynamic>false</Dynamic>
		</SavedProp>
		<SavedProp>
			<Position>
				<X>-1716.445</X>
				<Y>-564.654</Y>
				<Z>36.217</Z>
			</Position>
			<Rotation>
				<X>-3.522</X>
				<Y>-1.534</Y>
				<Z>-143.648</Z>
			</Rotation>
			<Hash>631705629</Hash>
			<Dynamic>false</Dynamic>
		</SavedProp>
		<SavedProp>
			<Position>
				<X>-2224.907</X>
				<Y>1078.252</Y>
				<Z>195.776</Z>
			</Position>
			<Rotation>
				<X>-3.795</X>
				<Y>4.252</Y>
				<Z>-27.861</Z>
			</Rotation>
			<Hash>631705629</Hash>
			<Dynamic>false</Dynamic>
		</SavedProp>
		<SavedProp>
			<Position>
				<X>-2230.832</X>
				<Y>1081.346</Y>
				<Z>196.267</Z>
			</Position>
			<Rotation>
				<X>-4.187</X>
				<Y>3.425</Y>
				<Z>-25.477</Z>
			</Rotation>
			<Hash>631705629</Hash>
			<Dynamic>false</Dynamic>
		</SavedProp>
		<SavedProp>
			<Position>
				<X>-2237.012</X>
				<Y>1083.862</Y>
				<Z>196.679</Z>
			</Position>
			<Rotation>
				<X>-3.988</X>
				<Y>2.821</Y>
				<Z>-17.104</Z>
			</Rotation>
			<Hash>631705629</Hash>
			<Dynamic>false</Dynamic>
		</SavedProp>
		<SavedProp>
			<Position>
				<X>-2243.460</X>
				<Y>1085.318</Y>
				<Z>197.043</Z>
			</Position>
			<Rotation>
				<X>-4.245</X>
				<Y>1.600</Y>
				<Z>-8.343</Z>
			</Rotation>
			<Hash>631705629</Hash>
			<Dynamic>false</Dynamic>
		</SavedProp>
		<SavedProp>
			<Position>
				<X>-2250.135</X>
				<Y>1085.527</Y>
				<Z>197.284</Z>
			</Position>
			<Rotation>
				<X>-4.050</X>
				<Y>2.558</Y>
				<Z>5.288</Z>
			</Rotation>
			<Hash>631705629</Hash>
			<Dynamic>false</Dynamic>
		</SavedProp>
		<SavedProp>
			<Position>
				<X>-2256.666</X>
				<Y>1084.300</Y>
				<Z>197.425</Z>
			</Position>
			<Rotation>
				<X>-4.336</X>
				<Y>1.430</Y>
				<Z>16.052</Z>
			</Rotation>
			<Hash>631705629</Hash>
			<Dynamic>false</Dynamic>
		</SavedProp>
		<SavedProp>
			<Position>
				<X>-2262.790</X>
				<Y>1081.755</Y>
				<Z>197.449</Z>
			</Position>
			<Rotation>
				<X>-4.281</X>
				<Y>0.041</Y>
				<Z>27.999</Z>
			</Rotation>
			<Hash>631705629</Hash>
			<Dynamic>false</Dynamic>
		</SavedProp>
		<SavedProp>
			<Position>
				<X>-2643.727</X>
				<Y>1500.773</Y>
				<Z>118.982</Z>
			</Position>
			<Rotation>
				<X>3.339</X>
				<Y>-8.479</Y>
				<Z>-38.555</Z>
			</Rotation>
			<Hash>631705629</Hash>
			<Dynamic>false</Dynamic>
		</SavedProp>
		<SavedProp>
			<Position>
				<X>-2638.584</X>
				<Y>1496.274</Y>
				<Z>120.056</Z>
			</Position>
			<Rotation>
				<X>-4.943</X>
				<Y>-9.782</Y>
				<Z>-42.426</Z>
			</Rotation>
			<Hash>631705629</Hash>
			<Dynamic>false</Dynamic>
		</SavedProp>
		<SavedProp>
			<Position>
				<X>-2633.968</X>
				<Y>1491.306</Y>
				<Z>121.182</Z>
			</Position>
			<Rotation>
				<X>-3.296</X>
				<Y>-8.643</Y>
				<Z>-52.652</Z>
			</Rotation>
			<Hash>631705629</Hash>
			<Dynamic>false</Dynamic>
		</SavedProp>
		<SavedProp>
			<Position>
				<X>-2630.476</X>
				<Y>1485.799</Y>
				<Z>122.205</Z>
			</Position>
			<Rotation>
				<X>-3.907</X>
				<Y>-8.715</Y>
				<Z>-63.100</Z>
			</Rotation>
			<Hash>631705629</Hash>
			<Dynamic>false</Dynamic>
		</SavedProp>
		<SavedProp>
			<Position>
				<X>-2670.955</X>
				<Y>1513.151</Y>
				<Z>113.155</Z>
			</Position>
			<Rotation>
				<X>-5.802</X>
				<Y>-8.120</Y>
				<Z>-13.615</Z>
			</Rotation>
			<Hash>631705629</Hash>
			<Dynamic>false</Dynamic>
		</SavedProp>
		<SavedProp>
			<Position>
				<X>-2677.647</X>
				<Y>1514.291</Y>
				<Z>112.118</Z>
			</Position>
			<Rotation>
				<X>-5.345</X>
				<Y>-10.200</Y>
				<Z>-7.680</Z>
			</Rotation>
			<Hash>631705629</Hash>
			<Dynamic>false</Dynamic>
		</SavedProp>
		<SavedProp>
			<Position>
				<X>-2684.454</X>
				<Y>1514.614</Y>
				<Z>110.911</Z>
			</Position>
			<Rotation>
				<X>-4.469</X>
				<Y>-10.630</Y>
				<Z>2.381</Z>
			</Rotation>
			<Hash>631705629</Hash>
			<Dynamic>false</Dynamic>
		</SavedProp>
		<SavedProp>
			<Position>
				<X>-2691.196</X>
				<Y>1513.717</Y>
				<Z>109.631</Z>
			</Position>
			<Rotation>
				<X>-4.798</X>
				<Y>-10.893</Y>
				<Z>13.139</Z>
			</Rotation>
			<Hash>631705629</Hash>
			<Dynamic>false</Dynamic>
		</SavedProp>
		<SavedProp>
			<Position>
				<X>-2697.734</X>
				<Y>1511.824</Y>
				<Z>108.346</Z>
			</Position>
			<Rotation>
				<X>-3.591</X>
				<Y>-10.992</Y>
				<Z>18.451</Z>
			</Rotation>
			<Hash>631705629</Hash>
			<Dynamic>false</Dynamic>
		</SavedProp>
		<SavedProp>
			<Position>
				<X>-2822.576</X>
				<Y>1283.141</Y>
				<Z>65.566</Z>
			</Position>
			<Rotation>
				<X>4.423</X>
				<Y>-10.402</Y>
				<Z>26.800</Z>
			</Rotation>
			<Hash>631705629</Hash>
			<Dynamic>false</Dynamic>
		</SavedProp>
		<SavedProp>
			<Position>
				<X>-2828.713</X>
				<Y>1280.372</Y>
				<Z>64.296</Z>
			</Position>
			<Rotation>
				<X>4.408</X>
				<Y>-10.374</Y>
				<Z>20.797</Z>
			</Rotation>
			<Hash>631705629</Hash>
			<Dynamic>false</Dynamic>
		</SavedProp>
		<SavedProp>
			<Position>
				<X>-2835.261</X>
				<Y>1278.429</Y>
				<Z>63.009</Z>
			</Position>
			<Rotation>
				<X>5.374</X>
				<Y>-10.419</Y>
				<Z>13.287</Z>
			</Rotation>
			<Hash>631705629</Hash>
			<Dynamic>false</Dynamic>
		</SavedProp>
		<SavedProp>
			<Position>
				<X>-2841.868</X>
				<Y>1277.027</Y>
				<Z>61.720</Z>
			</Position>
			<Rotation>
				<X>4.169</X>
				<Y>-10.321</Y>
				<Z>8.374</Z>
			</Rotation>
			<Hash>631705629</Hash>
			<Dynamic>false</Dynamic>
		</SavedProp>
		<SavedProp>
			<Position>
				<X>-2848.694</X>
				<Y>1276.439</Y>
				<Z>60.433</Z>
			</Position>
			<Rotation>
				<X>4.443</X>
				<Y>-10.532</Y>
				<Z>0.807</Z>
			</Rotation>
			<Hash>631705629</Hash>
			<Dynamic>false</Dynamic>
		</SavedProp>
	</DecorativeProps>
	<Trigger>
		<X>-3130.817</X>
		<Y>806.889</Y>
		<Z>16.540</Z>
	</Trigger>
	<Name>On the GOH</Name>
	<Description>The first time you almost plunge off a cliff, you'll forget about the stunning views and start to concentrate on the road. Dozens of hysterical city-dwellers compete for a small patch of asphalt in this long lap race for sports cars on the Great Ocean Highway and Banham Canyon.</Description>
</Race>