<?xml version="1.0" encoding="utf-8"?>
<Race xmlns:xsd="http://www.w3.org/2001/XMLSchema" xmlns:xsi="http://www.w3.org/2001/XMLSchema-instance">
  <Checkpoints>
    <Vector3>
      <X>2625.804</X>
      <Y>5109.242</Y>
      <Z>43.850</Z>
    </Vector3>
    <Vector3>
      <X>2729.073</X>
      <Y>5085.219</Y>
      <Z>42.539</Z>
    </Vector3>
    <Vector3>
      <X>2794.645</X>
      <Y>4948.897</Y>
      <Z>33.415</Z>
    </Vector3>
    <Vector3>
      <X>2878.389</X>
      <Y>5024.830</Y>
      <Z>31.476</Z>
    </Vector3>
    <Vector3>
      <X>3060.546</X>
      <Y>5044.604</Y>
      <Z>24.856</Z>
    </Vector3>
    <Vector3>
      <X>3169.034</X>
      <Y>5111.732</Y>
      <Z>17.985</Z>
    </Vector3>
    <Vector3>
      <X>3258.782</X>
      <Y>5142.751</Y>
      <Z>19.310</Z>
    </Vector3>
    <Vector3>
      <X>3223.111</X>
      <Y>5225.697</Y>
      <Z>22.385</Z>
    </Vector3>
    <Vector3>
      <X>3161.522</X>
      <Y>5264.385</Y>
      <Z>29.368</Z>
    </Vector3>
    <Vector3>
      <X>3144.190</X>
      <Y>5347.065</Y>
      <Z>28.242</Z>
    </Vector3>
    <Vector3>
      <X>3225.624</X>
      <Y>5389.641</Y>
      <Z>19.826</Z>
    </Vector3>
    <Vector3>
      <X>3336.797</X>
      <Y>5469.191</Y>
      <Z>19.397</Z>
    </Vector3>
    <Vector3>
      <X>3349.384</X>
      <Y>5569.021</Y>
      <Z>18.741</Z>
    </Vector3>
    <Vector3>
      <X>3342.051</X>
      <Y>5684.283</Y>
      <Z>10.222</Z>
    </Vector3>
    <Vector3>
      <X>3321.747</X>
      <Y>5872.377</Y>
      <Z>64.264</Z>
    </Vector3>
    <Vector3>
      <X>3209.431</X>
      <Y>5982.769</Y>
      <Z>106.751</Z>
    </Vector3>
    <Vector3>
      <X>3082.926</X>
      <Y>6040.073</Y>
      <Z>127.966</Z>
    </Vector3>
    <Vector3>
      <X>3044.347</X>
      <Y>6221.905</Y>
      <Z>109.080</Z>
    </Vector3>
    <Vector3>
      <X>2975.923</X>
      <Y>6231.562</Y>
      <Z>88.895</Z>
    </Vector3>
    <Vector3>
      <X>2891.666</X>
      <Y>6298.064</Y>
      <Z>63.175</Z>
    </Vector3>
    <Vector3>
      <X>2816.371</X>
      <Y>6335.226</Y>
      <Z>87.787</Z>
    </Vector3>
    <Vector3>
      <X>2669.293</X>
      <Y>6355.754</Y>
      <Z>121.106</Z>
    </Vector3>
    <Vector3>
      <X>2625.476</X>
      <Y>6279.021</Y>
      <Z>126.649</Z>
    </Vector3>
    <Vector3>
      <X>2594.460</X>
      <Y>6175.348</Y>
      <Z>167.168</Z>
    </Vector3>
    <Vector3>
      <X>2647.760</X>
      <Y>6191.154</Y>
      <Z>194.291</Z>
    </Vector3>
    <Vector3>
      <X>2703.907</X>
      <Y>6151.368</Y>
      <Z>235.657</Z>
    </Vector3>
    <Vector3>
      <X>2754.746</X>
      <Y>6118.924</Y>
      <Z>270.858</Z>
    </Vector3>
    <Vector3>
      <X>2826.359</X>
      <Y>5995.512</Y>
      <Z>338.474</Z>
    </Vector3>
    <Vector3>
      <X>2862.614</X>
      <Y>5912.085</Y>
      <Z>364.579</Z>
    </Vector3>
    <Vector3>
      <X>2914.510</X>
      <Y>5866.950</Y>
      <Z>354.092</Z>
    </Vector3>
    <Vector3>
      <X>2932.612</X>
      <Y>5767.888</Y>
      <Z>323.674</Z>
    </Vector3>
    <Vector3>
      <X>2950.947</X>
      <Y>5679.061</Y>
      <Z>260.119</Z>
    </Vector3>
    <Vector3>
      <X>2954.501</X>
      <Y>5504.938</Y>
      <Z>174.581</Z>
    </Vector3>
    <Vector3>
      <X>2984.660</X>
      <Y>5460.240</Y>
      <Z>146.470</Z>
    </Vector3>
    <Vector3>
      <X>2960.612</X>
      <Y>5342.791</Y>
      <Z>101.270</Z>
    </Vector3>
    <Vector3>
      <X>2868.842</X>
      <Y>5289.436</Y>
      <Z>95.227</Z>
    </Vector3>
    <Vector3>
      <X>2666.475</X>
      <Y>5125.194</Y>
      <Z>44.464</Z>
    </Vector3>
  </Checkpoints>
  <SpawnPoints>
    <SpawnPoint>
      <Position>
        <X>2623.517</X>
        <Y>5117.946</Y>
        <Z>43.788</Z>
      </Position>
      <Heading>-75.282</Heading>
    </SpawnPoint>
    <SpawnPoint>
      <Position>
        <X>2625.804</X>
        <Y>5109.242</Y>
        <Z>43.850</Z>
      </Position>
      <Heading>-75.282</Heading>
    </SpawnPoint>
    <SpawnPoint>
      <Position>
        <X>2616.875</X>
        <Y>5111.549</Y>
        <Z>43.756</Z>
      </Position>
      <Heading>-75.282</Heading>
    </SpawnPoint>
    <SpawnPoint>
      <Position>
        <X>2619.161</X>
        <Y>5102.844</Y>
        <Z>43.758</Z>
      </Position>
      <Heading>-75.282</Heading>
    </SpawnPoint>
    <SpawnPoint>
      <Position>
        <X>2607.946</X>
        <Y>5113.856</Y>
        <Z>43.809</Z>
      </Position>
      <Heading>-75.282</Heading>
    </SpawnPoint>
    <SpawnPoint>
      <Position>
        <X>2610.232</X>
        <Y>5105.151</Y>
        <Z>43.813</Z>
      </Position>
      <Heading>-75.282</Heading>
    </SpawnPoint>
    <SpawnPoint>
      <Position>
        <X>2601.303</X>
        <Y>5107.458</Y>
        <Z>43.769</Z>
      </Position>
      <Heading>-75.282</Heading>
    </SpawnPoint>
    <SpawnPoint>
      <Position>
        <X>2603.590</X>
        <Y>5098.753</Y>
        <Z>43.775</Z>
      </Position>
      <Heading>-75.282</Heading>
    </SpawnPoint>
    <SpawnPoint>
      <Position>
        <X>2592.374</X>
        <Y>5109.766</Y>
        <Z>43.722</Z>
      </Position>
      <Heading>-75.282</Heading>
    </SpawnPoint>
    <SpawnPoint>
      <Position>
        <X>2594.661</X>
        <Y>5101.061</Y>
        <Z>43.769</Z>
      </Position>
      <Heading>-75.282</Heading>
    </SpawnPoint>
    <SpawnPoint>
      <Position>
        <X>2585.731</X>
        <Y>5103.368</Y>
        <Z>43.742</Z>
      </Position>
      <Heading>-75.282</Heading>
    </SpawnPoint>
    <SpawnPoint>
      <Position>
        <X>2588.018</X>
        <Y>5094.663</Y>
        <Z>43.650</Z>
      </Position>
      <Heading>-75.282</Heading>
    </SpawnPoint>
    <SpawnPoint>
      <Position>
        <X>2576.802</X>
        <Y>5105.675</Y>
        <Z>43.649</Z>
      </Position>
      <Heading>-75.282</Heading>
    </SpawnPoint>
    <SpawnPoint>
      <Position>
        <X>2579.089</X>
        <Y>5096.970</Y>
        <Z>43.772</Z>
      </Position>
      <Heading>-75.282</Heading>
    </SpawnPoint>
    <SpawnPoint>
      <Position>
        <X>2570.160</X>
        <Y>5099.277</Y>
        <Z>43.663</Z>
      </Position>
      <Heading>-75.282</Heading>
    </SpawnPoint>
    <SpawnPoint>
      <Position>
        <X>2572.446</X>
        <Y>5090.573</Y>
        <Z>43.555</Z>
      </Position>
      <Heading>-75.282</Heading>
    </SpawnPoint>
  </SpawnPoints>
  <AvailableVehicles>
    <VehicleHash>Comet4</VehicleHash>
    <VehicleHash>Drafter</VehicleHash>
    <VehicleHash>GB200</VehicleHash>
    <VehicleHash>Kuruma</VehicleHash>
    <VehicleHash>Kuruma2</VehicleHash>
    <VehicleHash>Lynx</VehicleHash>
    <VehicleHash>Massacro2</VehicleHash>
    <VehicleHash>Omnis</VehicleHash>
    <VehicleHash>Sultan2</VehicleHash>
    <VehicleHash>Tampa2</VehicleHash>
    <VehicleHash>Tropos</VehicleHash>
    <VehicleHash>ZR380</VehicleHash>
  </AvailableVehicles>
  <LapsAvailable>false</LapsAvailable>
  <DecorativeProps>
    <SavedProp>
      <Position>
        <X>2686.484</X>
        <Y>5148.549</Y>
        <Z>42.279</Z>
      </Position>
      <Rotation>
        <X>0.0</X>
        <Y>0.0</Y>
        <Z>135.959</Z>
      </Rotation>
      <Hash>55777251</Hash>
      <Dynamic>true</Dynamic>
    </SavedProp>
    <SavedProp>
      <Position>
        <X>3308.405</X>
        <Y>5947.181</Y>
        <Z>88.038</Z>
      </Position>
      <Rotation>
        <X>0.0</X>
        <Y>0.0</Y>
        <Z>132.759</Z>
      </Rotation>
      <Hash>-928338834</Hash>
      <Dynamic>true</Dynamic>
    </SavedProp>
    <SavedProp>
      <Position>
        <X>3244.589</X>
        <Y>5985.501</Y>
        <Z>89.063</Z>
      </Position>
      <Rotation>
        <X>14.519</X>
        <Y>-18.690</Y>
        <Z>179.161</Z>
      </Rotation>
      <Hash>-928338834</Hash>
      <Dynamic>true</Dynamic>
    </SavedProp>
    <SavedProp>
      <Position>
        <X>3112.254</X>
        <Y>5980.764</Y>
        <Z>142.041</Z>
      </Position>
      <Rotation>
        <X>19.818</X>
        <Y>7.455</Y>
        <Z>-172.545</Z>
      </Rotation>
      <Hash>-928338834</Hash>
      <Dynamic>true</Dynamic>
    </SavedProp>
    <SavedProp>
      <Position>
        <X>3114.178</X>
        <Y>5981.111</Y>
        <Z>142.275</Z>
      </Position>
      <Rotation>
        <X>19.803</X>
        <Y>7.298</Y>
        <Z>-172.517</Z>
      </Rotation>
      <Hash>-928338834</Hash>
      <Dynamic>true</Dynamic>
    </SavedProp>
    <SavedProp>
      <Position>
        <X>3116.099</X>
        <Y>5981.479</Y>
        <Z>142.476</Z>
      </Position>
      <Rotation>
        <X>21.586</X>
        <Y>4.628</Y>
        <Z>-172.124</Z>
      </Rotation>
      <Hash>-928338834</Hash>
      <Dynamic>true</Dynamic>
    </SavedProp>
    <SavedProp>
      <Position>
        <X>3049.686</X>
        <Y>6220.146</Y>
        <Z>111.299</Z>
      </Position>
      <Rotation>
        <X>22.292</X>
        <Y>1.635</Y>
        <Z>-171.563</Z>
      </Rotation>
      <Hash>-928338834</Hash>
      <Dynamic>true</Dynamic>
    </SavedProp>
    <SavedProp>
      <Position>
        <X>3047.512</X>
        <Y>6220.206</Y>
        <Z>111.036</Z>
      </Position>
      <Rotation>
        <X>25.617</X>
        <Y>8.133</Y>
        <Z>-173.093</Z>
      </Rotation>
      <Hash>-928338834</Hash>
      <Dynamic>true</Dynamic>
    </SavedProp>
    <SavedProp>
      <Position>
        <X>2884.598</X>
        <Y>6308.603</Y>
        <Z>59.079</Z>
      </Position>
      <Rotation>
        <X>21.817</X>
        <Y>-6.013</Y>
        <Z>-174.881</Z>
      </Rotation>
      <Hash>-928338834</Hash>
      <Dynamic>true</Dynamic>
    </SavedProp>
    <SavedProp>
      <Position>
        <X>2886.900</X>
        <Y>6308.832</Y>
        <Z>58.955</Z>
      </Position>
      <Rotation>
        <X>18.906</X>
        <Y>0.479</Y>
        <Z>-176.121</Z>
      </Rotation>
      <Hash>-928338834</Hash>
      <Dynamic>true</Dynamic>
    </SavedProp>
    <SavedProp>
      <Position>
        <X>2889.137</X>
        <Y>6309.144</Y>
        <Z>58.858</Z>
      </Position>
      <Rotation>
        <X>20.720</X>
        <Y>-5.142</Y>
        <Z>-175.101</Z>
      </Rotation>
      <Hash>-928338834</Hash>
      <Dynamic>true</Dynamic>
    </SavedProp>
    <SavedProp>
      <Position>
        <X>2891.606</X>
        <Y>6309.720</Y>
        <Z>58.480</Z>
      </Position>
      <Rotation>
        <X>20.720</X>
        <Y>-5.142</Y>
        <Z>-175.101</Z>
      </Rotation>
      <Hash>-928338834</Hash>
      <Dynamic>true</Dynamic>
    </SavedProp>
    <SavedProp>
      <Position>
        <X>2742.916</X>
        <Y>6364.977</Y>
        <Z>109.812</Z>
      </Position>
      <Rotation>
        <X>11.886</X>
        <Y>-6.679</Y>
        <Z>151.855</Z>
      </Rotation>
      <Hash>-928338834</Hash>
      <Dynamic>true</Dynamic>
    </SavedProp>
    <SavedProp>
      <Position>
        <X>2699.095</X>
        <Y>6378.938</Y>
        <Z>119.862</Z>
      </Position>
      <Rotation>
        <X>16.933</X>
        <Y>-7.827</Y>
        <Z>-151.675</Z>
      </Rotation>
      <Hash>-928338834</Hash>
      <Dynamic>true</Dynamic>
    </SavedProp>
    <SavedProp>
      <Position>
        <X>2574.588</X>
        <Y>6206.693</Y>
        <Z>155.894</Z>
      </Position>
      <Rotation>
        <X>8.358</X>
        <Y>5.618</Y>
        <Z>-153.252</Z>
      </Rotation>
      <Hash>812376260</Hash>
      <Dynamic>true</Dynamic>
    </SavedProp>
    <SavedProp>
      <Position>
        <X>2598.505</X>
        <Y>6178.483</Y>
        <Z>167.248</Z>
      </Position>
      <Rotation>
        <X>11.968</X>
        <Y>14.794</Y>
        <Z>-154.401</Z>
      </Rotation>
      <Hash>812376260</Hash>
      <Dynamic>true</Dynamic>
    </SavedProp>
    <SavedProp>
      <Position>
        <X>2694.371</X>
        <Y>6153.312</Y>
        <Z>231.135</Z>
      </Position>
      <Rotation>
        <X>-12.626</X>
        <Y>-10.731</Y>
        <Z>21.567</Z>
      </Rotation>
      <Hash>-928338834</Hash>
      <Dynamic>true</Dynamic>
    </SavedProp>
    <SavedProp>
      <Position>
        <X>2693.962</X>
        <Y>6152.870</Y>
        <Z>231.080</Z>
      </Position>
      <Rotation>
        <X>13.395</X>
        <Y>9.083</Y>
        <Z>-149.911</Z>
      </Rotation>
      <Hash>-928338834</Hash>
      <Dynamic>true</Dynamic>
    </SavedProp>
    <SavedProp>
      <Position>
        <X>2823.356</X>
        <Y>5976.583</Y>
        <Z>348.786</Z>
      </Position>
      <Rotation>
        <X>24.964</X>
        <Y>-3.545</Y>
        <Z>133.543</Z>
      </Rotation>
      <Hash>-928338834</Hash>
      <Dynamic>true</Dynamic>
    </SavedProp>
    <SavedProp>
      <Position>
        <X>2824.852</X>
        <Y>5974.936</Y>
        <Z>348.708</Z>
      </Position>
      <Rotation>
        <X>25.921</X>
        <Y>-1.241</Y>
        <Z>133.043</Z>
      </Rotation>
      <Hash>-928338834</Hash>
      <Dynamic>true</Dynamic>
    </SavedProp>
    <SavedProp>
      <Position>
        <X>2826.208</X>
        <Y>5973.565</Y>
        <Z>348.874</Z>
      </Position>
      <Rotation>
        <X>14.013</X>
        <Y>9.056</Y>
        <Z>131.643</Z>
      </Rotation>
      <Hash>-928338834</Hash>
      <Dynamic>true</Dynamic>
    </SavedProp>
    <SavedProp>
      <Position>
        <X>2872.988</X>
        <Y>5902.521</Y>
        <Z>364.820</Z>
      </Position>
      <Rotation>
        <X>-12.024</X>
        <Y>2.385</Y>
        <Z>158.609</Z>
      </Rotation>
      <Hash>-928338834</Hash>
      <Dynamic>true</Dynamic>
    </SavedProp>
    <SavedProp>
      <Position>
        <X>2870.379</X>
        <Y>5904.229</Y>
        <Z>364.826</Z>
      </Position>
      <Rotation>
        <X>-17.482</X>
        <Y>-1.441</Y>
        <Z>158.136</Z>
      </Rotation>
      <Hash>-928338834</Hash>
      <Dynamic>true</Dynamic>
    </SavedProp>
    <SavedProp>
      <Position>
        <X>2867.306</X>
        <Y>5905.609</Y>
        <Z>364.877</Z>
      </Position>
      <Rotation>
        <X>-16.415</X>
        <Y>5.848</Y>
        <Z>159.202</Z>
      </Rotation>
      <Hash>-928338834</Hash>
      <Dynamic>true</Dynamic>
    </SavedProp>
    <SavedProp>
      <Position>
        <X>2919.730</X>
        <Y>5861.882</Y>
        <Z>351.659</Z>
      </Position>
      <Rotation>
        <X>-5.093</X>
        <Y>-18.020</Y>
        <Z>91.149</Z>
      </Rotation>
      <Hash>-928338834</Hash>
      <Dynamic>true</Dynamic>
    </SavedProp>
    <SavedProp>
      <Position>
        <X>2919.376</X>
        <Y>5864.987</Y>
        <Z>352.640</Z>
      </Position>
      <Rotation>
        <X>-5.173</X>
        <Y>-17.653</Y>
        <Z>91.154</Z>
      </Rotation>
      <Hash>-928338834</Hash>
      <Dynamic>true</Dynamic>
    </SavedProp>
    <SavedProp>
      <Position>
        <X>2919.819</X>
        <Y>5859.479</Y>
        <Z>350.870</Z>
      </Position>
      <Rotation>
        <X>-6.108</X>
        <Y>-18.330</Y>
        <Z>90.971</Z>
      </Rotation>
      <Hash>-928338834</Hash>
      <Dynamic>true</Dynamic>
    </SavedProp>
    <SavedProp>
      <Position>
        <X>2940.509</X>
        <Y>5758.834</Y>
        <Z>320.087</Z>
      </Position>
      <Rotation>
        <X>5.878</X>
        <Y>12.695</Y>
        <Z>-4.697</Z>
      </Rotation>
      <Hash>-928338834</Hash>
      <Dynamic>true</Dynamic>
    </SavedProp>
    <SavedProp>
      <Position>
        <X>2938.731</X>
        <Y>5759.188</Y>
        <Z>320.517</Z>
      </Position>
      <Rotation>
        <X>5.878</X>
        <Y>12.695</Y>
        <Z>-4.697</Z>
      </Rotation>
      <Hash>-928338834</Hash>
      <Dynamic>true</Dynamic>
    </SavedProp>
    <SavedProp>
      <Position>
        <X>2936.850</X>
        <Y>5759.770</Y>
        <Z>321.123</Z>
      </Position>
      <Rotation>
        <X>1.018</X>
        <Y>27.116</Y>
        <Z>-4.288</Z>
      </Rotation>
      <Hash>-928338834</Hash>
      <Dynamic>true</Dynamic>
    </SavedProp>
    <SavedProp>
      <Position>
        <X>2991.255</X>
        <Y>5769.543</Y>
        <Z>301.838</Z>
      </Position>
      <Rotation>
        <X>2.469</X>
        <Y>-15.161</Y>
        <Z>117.086</Z>
      </Rotation>
      <Hash>-928338834</Hash>
      <Dynamic>true</Dynamic>
    </SavedProp>
    <SavedProp>
      <Position>
        <X>2992.273</X>
        <Y>5767.524</Y>
        <Z>301.248</Z>
      </Position>
      <Rotation>
        <X>6.551</X>
        <Y>-15.655</Y>
        <Z>117.659</Z>
      </Rotation>
      <Hash>-928338834</Hash>
      <Dynamic>true</Dynamic>
    </SavedProp>
    <SavedProp>
      <Position>
        <X>2952.159</X>
        <Y>5678.947</Y>
        <Z>259.539</Z>
      </Position>
      <Rotation>
        <X>-14.034</X>
        <Y>-12.992</Y>
        <Z>123.551</Z>
      </Rotation>
      <Hash>-928338834</Hash>
      <Dynamic>true</Dynamic>
    </SavedProp>
    <SavedProp>
      <Position>
        <X>2953.690</X>
        <Y>5677.444</Y>
        <Z>259.105</Z>
      </Position>
      <Rotation>
        <X>-15.142</X>
        <Y>-14.439</Y>
        <Z>123.228</Z>
      </Rotation>
      <Hash>-928338834</Hash>
      <Dynamic>true</Dynamic>
    </SavedProp>
    <SavedProp>
      <Position>
        <X>2954.947</X>
        <Y>5674.955</Y>
        <Z>258.199</Z>
      </Position>
      <Rotation>
        <X>-21.099</X>
        <Y>-17.106</Y>
        <Z>121.949</Z>
      </Rotation>
      <Hash>-928338834</Hash>
      <Dynamic>true</Dynamic>
    </SavedProp>
    <SavedProp>
      <Position>
        <X>2996.809</X>
        <Y>5620.839</Y>
        <Z>230.069</Z>
      </Position>
      <Rotation>
        <X>31.156</X>
        <Y>14.683</Y>
        <Z>41.843</Z>
      </Rotation>
      <Hash>-928338834</Hash>
      <Dynamic>true</Dynamic>
    </SavedProp>
    <SavedProp>
      <Position>
        <X>2998.764</X>
        <Y>5623.055</Y>
        <Z>229.666</Z>
      </Position>
      <Rotation>
        <X>30.098</X>
        <Y>2.486</Y>
        <Z>50.489</Z>
      </Rotation>
      <Hash>-928338834</Hash>
      <Dynamic>true</Dynamic>
    </SavedProp>
    <SavedProp>
      <Position>
        <X>3054.185</X>
        <Y>5694.930</Y>
        <Z>225.855</Z>
      </Position>
      <Rotation>
        <X>7.964</X>
        <Y>8.772</Y>
        <Z>-64.255</Z>
      </Rotation>
      <Hash>-928338834</Hash>
      <Dynamic>true</Dynamic>
    </SavedProp>
    <SavedProp>
      <Position>
        <X>3054.845</X>
        <Y>5691.840</Y>
        <Z>225.263</Z>
      </Position>
      <Rotation>
        <X>4.601</X>
        <Y>11.885</Y>
        <Z>-84.522</Z>
      </Rotation>
      <Hash>-928338834</Hash>
      <Dynamic>true</Dynamic>
    </SavedProp>
    <SavedProp>
      <Position>
        <X>3054.146</X>
        <Y>5688.708</Y>
        <Z>224.733</Z>
      </Position>
      <Rotation>
        <X>5.181</X>
        <Y>9.072</Y>
        <Z>-104.854</Z>
      </Rotation>
      <Hash>-928338834</Hash>
      <Dynamic>true</Dynamic>
    </SavedProp>
    <SavedProp>
      <Position>
        <X>3043.154</X>
        <Y>5542.034</Y>
        <Z>192.347</Z>
      </Position>
      <Rotation>
        <X>16.538</X>
        <Y>8.887</Y>
        <Z>-149.736</Z>
      </Rotation>
      <Hash>-1601837956</Hash>
      <Dynamic>true</Dynamic>
    </SavedProp>
    <SavedProp>
      <Position>
        <X>3046.549</X>
        <Y>5545.764</Y>
        <Z>193.075</Z>
      </Position>
      <Rotation>
        <X>11.047</X>
        <Y>10.847</Y>
        <Z>-149.495</Z>
      </Rotation>
      <Hash>-1601837956</Hash>
      <Dynamic>true</Dynamic>
    </SavedProp>
    <SavedProp>
      <Position>
        <X>2944.737</X>
        <Y>5439.225</Y>
        <Z>162.638</Z>
      </Position>
      <Rotation>
        <X>-15.333</X>
        <Y>-10.487</Y>
        <Z>166.942</Z>
      </Rotation>
      <Hash>2084346858</Hash>
      <Dynamic>true</Dynamic>
    </SavedProp>
    <SavedProp>
      <Position>
        <X>2954.325</X>
        <Y>5441.391</Y>
        <Z>160.715</Z>
      </Position>
      <Rotation>
        <X>4.828</X>
        <Y>-7.100</Y>
        <Z>-138.543</Z>
      </Rotation>
      <Hash>2084346858</Hash>
      <Dynamic>true</Dynamic>
    </SavedProp>
    <SavedProp>
      <Position>
        <X>3005.268</X>
        <Y>5429.762</Y>
        <Z>128.600</Z>
      </Position>
      <Rotation>
        <X>-11.827</X>
        <Y>-3.525</Y>
        <Z>-121.207</Z>
      </Rotation>
      <Hash>-1601837956</Hash>
      <Dynamic>true</Dynamic>
    </SavedProp>
    <SavedProp>
      <Position>
        <X>2952.134</X>
        <Y>5314.189</Y>
        <Z>100.927</Z>
      </Position>
      <Rotation>
        <X>16.199</X>
        <Y>-1.792</Y>
        <Z>-153.787</Z>
      </Rotation>
      <Hash>-1601837956</Hash>
      <Dynamic>true</Dynamic>
    </SavedProp>
    <SavedProp>
      <Position>
        <X>2945.197</X>
        <Y>5310.837</Y>
        <Z>100.065</Z>
      </Position>
      <Rotation>
        <X>4.265</X>
        <Y>1.903</Y>
        <Z>-162.513</Z>
      </Rotation>
      <Hash>-1601837956</Hash>
      <Dynamic>true</Dynamic>
    </SavedProp>
    <SavedProp>
      <Position>
        <X>2940.150</X>
        <Y>5308.436</Y>
        <Z>99.994</Z>
      </Position>
      <Rotation>
        <X>10.975</X>
        <Y>3.815</Y>
        <Z>-164.809</Z>
      </Rotation>
      <Hash>-1601837956</Hash>
      <Dynamic>true</Dynamic>
    </SavedProp>
    <SavedProp>
      <Position>
        <X>2724.859</X>
        <Y>5205.281</Y>
        <Z>46.416</Z>
      </Position>
      <Rotation>
        <X>5.498</X>
        <Y>-15.075</Y>
        <Z>92.686</Z>
      </Rotation>
      <Hash>2084346858</Hash>
      <Dynamic>true</Dynamic>
    </SavedProp>
    <SavedProp>
      <Position>
        <X>2720.069</X>
        <Y>5195.733</Y>
        <Z>44.623</Z>
      </Position>
      <Rotation>
        <X>1.550</X>
        <Y>-9.390</Y>
        <Z>58.485</Z>
      </Rotation>
      <Hash>2084346858</Hash>
      <Dynamic>true</Dynamic>
    </SavedProp>
  </DecorativeProps>
  <Trigger>
    <X>2621.065</X>
    <Y>5135.752</Y>
    <Z>43.799</Z>
  </Trigger>
  <Name>Rally Xtreme</Name>
  <Description>Por esta ladera veras que el camino ya es poco visible, usa a t u compañero de guia y ojo a los terraplén, un paso en falso p ara disfrutar de vueltas de campana interminables.</Description>
</Race>