<?xml version="1.0" encoding="utf-8"?>
<Race xmlns:xsd="http://www.w3.org/2001/XMLSchema" xmlns:xsi="http://www.w3.org/2001/XMLSchema-instance">
	<Checkpoints>
		<Vector3>
			<X>-1812.285</X>
			<Y>761.214</Y>
			<Z>134.793</Z>
		</Vector3>
		<Vector3>
			<X>-1928.590</X>
			<Y>663.098</Y>
			<Z>124.023</Z>
		</Vector3>
		<Vector3>
			<X>-1985.443</X>
			<Y>478.637</Y>
			<Z>102.987</Z>
		</Vector3>
		<Vector3>
			<X>-1964.704</X>
			<Y>343.545</Y>
			<Z>89.508</Z>
		</Vector3>
		<Vector3>
			<X>-1910.130</X>
			<Y>189.118</Y>
			<Z>82.660</Z>
		</Vector3>
		<Vector3>
			<X>-1744.199</X>
			<Y>85.986</Y>
			<Z>66.491</Z>
		</Vector3>
		<Vector3>
			<X>-1573.231</X>
			<Y>169.426</Y>
			<Z>57.274</Z>
		</Vector3>
		<Vector3>
			<X>-1462.560</X>
			<Y>259.320</Y>
			<Z>60.465</Z>
		</Vector3>
		<Vector3>
			<X>-1390.753</X>
			<Y>364.024</Y>
			<Z>62.802</Z>
		</Vector3>
		<Vector3>
			<X>-1234.652</X>
			<Y>402.853</Y>
			<Z>74.764</Z>
		</Vector3>
		<Vector3>
			<X>-1085.581</X>
			<Y>393.235</Y>
			<Z>67.820</Z>
		</Vector3>
		<Vector3>
			<X>-1085.357</X>
			<Y>241.488</Y>
			<Z>62.646</Z>
		</Vector3>
		<Vector3>
			<X>-1008.846</X>
			<Y>80.312</Y>
			<Z>50.925</Z>
		</Vector3>
		<Vector3>
			<X>-910.080</X>
			<Y>-74.321</Y>
			<Z>37.179</Z>
		</Vector3>
		<Vector3>
			<X>-803.931</X>
			<Y>-272.645</Y>
			<Z>35.976</Z>
		</Vector3>
		<Vector3>
			<X>-822.713</X>
			<Y>-360.906</Y>
			<Z>36.787</Z>
		</Vector3>
		<Vector3>
			<X>-952.123</X>
			<Y>-428.856</Y>
			<Z>36.871</Z>
		</Vector3>
		<Vector3>
			<X>-844.954</X>
			<Y>-631.414</Y>
			<Z>27.374</Z>
		</Vector3>
		<Vector3>
			<X>-643.610</X>
			<Y>-662.782</Y>
			<Z>30.713</Z>
		</Vector3>
		<Vector3>
			<X>-474.807</X>
			<Y>-658.514</Y>
			<Z>31.593</Z>
		</Vector3>
		<Vector3>
			<X>-319.905</X>
			<Y>-658.654</Y>
			<Z>31.733</Z>
		</Vector3>
		<Vector3>
			<X>-163.210</X>
			<Y>-709.743</Y>
			<Z>33.568</Z>
		</Vector3>
		<Vector3>
			<X>-74.780</X>
			<Y>-738.215</Y>
			<Z>32.910</Z>
		</Vector3>
		<Vector3>
			<X>26.019</X>
			<Y>-767.183</Y>
			<Z>30.633</Z>
		</Vector3>
		<Vector3>
			<X>73.518</X>
			<Y>-695.066</Y>
			<Z>30.605</Z>
		</Vector3>
		<Vector3>
			<X>189.023</X>
			<Y>-725.676</Y>
			<Z>33.199</Z>
		</Vector3>
		<Vector3>
			<X>234.446</X>
			<Y>-625.840</Y>
			<Z>39.775</Z>
		</Vector3>
		<Vector3>
			<X>172.350</X>
			<Y>-597.249</Y>
			<Z>42.538</Z>
		</Vector3>
		<Vector3>
			<X>99.841</X>
			<Y>-576.610</Y>
			<Z>42.772</Z>
		</Vector3>
		<Vector3>
			<X>38.456</X>
			<Y>-725.151</Y>
			<Z>43.236</Z>
		</Vector3>
	</Checkpoints>
	<SpawnPoints>
		<SpawnPoint>
			<Position>
				<X>-1807.358</X>
				<Y>762.230</Y>
				<Z>135.141</Z>
			</Position>
			<Heading>128.214</Heading>
		</SpawnPoint>
		<SpawnPoint>
			<Position>
				<X>-1803.816</X>
				<Y>770.745</Y>
				<Z>135.665</Z>
			</Position>
			<Heading>128.214</Heading>
		</SpawnPoint>
		<SpawnPoint>
			<Position>
				<X>-1794.708</X>
				<Y>772.189</Y>
				<Z>136.185</Z>
			</Position>
			<Heading>128.214</Heading>
		</SpawnPoint>
		<SpawnPoint>
			<Position>
				<X>-1791.166</X>
				<Y>780.705</Y>
				<Z>136.698</Z>
			</Position>
			<Heading>128.214</Heading>
		</SpawnPoint>
		<SpawnPoint>
			<Position>
				<X>-1782.058</X>
				<Y>782.149</Y>
				<Z>137.277</Z>
			</Position>
			<Heading>128.214</Heading>
		</SpawnPoint>
		<SpawnPoint>
			<Position>
				<X>-1778.516</X>
				<Y>790.664</Y>
				<Z>137.849</Z>
			</Position>
			<Heading>128.214</Heading>
		</SpawnPoint>
		<SpawnPoint>
			<Position>
				<X>-1769.408</X>
				<Y>792.108</Y>
				<Z>138.450</Z>
			</Position>
			<Heading>128.214</Heading>
		</SpawnPoint>
		<SpawnPoint>
			<Position>
				<X>-1765.867</X>
				<Y>800.623</Y>
				<Z>139.076</Z>
			</Position>
			<Heading>128.214</Heading>
		</SpawnPoint>
	</SpawnPoints>
	<AvailableVehicles>
		<VehicleHash>Tyrus</VehicleHash>
		<VehicleHash>Penetrator</VehicleHash>
	</AvailableVehicles>
	<LapsAvailable>false</LapsAvailable>
	<DecorativeProps>
	</DecorativeProps>
	<Trigger>
		<X>-1796.617</X>
		<Y>806.294</Y>
		<Z>137.513</Z>
	</Trigger>
	<Name>The City Commute</Name>
	<Description>Your alarm should have gone off hours ago, your mouth tastes like a donkey pissed in it (because one did), and you've got a marketing presentation in ten minutes - point to point from the suburbs to the city for cars and bikes. </Description>
</Race>