<?xml version="1.0" encoding="utf-8"?>
<Race xmlns:xsd="http://www.w3.org/2001/XMLSchema" xmlns:xsi="http://www.w3.org/2001/XMLSchema-instance">
  <Checkpoints>
    <Vector3>
      <X>-493.158234</X>
      <Y>1076.82788</Y>
      <Z>366.46698</Z>
    </Vector3>
    <Vector3>
      <X>-341.407349</X>
      <Y>923.0254</Y>
      <Z>254.768387</Z>
    </Vector3>
    <Vector3>
      <X>-198.893036</X>
      <Y>775.6552</Y>
      <Z>196.509445</Z>
    </Vector3>
    <Vector3>
      <X>-87.91721</X>
      <Y>707.105</Y>
      <Z>196.463989</Z>
    </Vector3>
    <Vector3>
      <X>11.8945045</X>
      <Y>656.779358</Y>
      <Z>196.670135</Z>
    </Vector3>
    <Vector3>
      <X>61.7226944</X>
      <Y>787.839844</Y>
      <Z>196.7497</Z>
    </Vector3>
    <Vector3>
      <X>64.9053</X>
      <Y>907.620667</Y>
      <Z>199.027161</Z>
    </Vector3>
    <Vector3>
      <X>10.220192</X>
      <Y>1030.63049</Y>
      <Z>251.346085</Z>
    </Vector3>
    <Vector3>
      <X>-107.22261</X>
      <Y>1064.14124</Y>
      <Z>251.304977</Z>
    </Vector3>
    <Vector3>
      <X>-264.498627</X>
      <Y>1042.77759</Y>
      <Z>266.41925</Z>
    </Vector3>
    <Vector3>
      <X>-333.5237</X>
      <Y>986.0609</Y>
      <Z>265.262451</Z>
    </Vector3>
    <Vector3>
      <X>-412.952148</X>
      <Y>909.2078</Y>
      <Z>265.9589</Z>
    </Vector3>
    <Vector3>
      <X>-825.6041</X>
      <Y>592.2881</Y>
      <Z>339.827148</Z>
    </Vector3>
    <Vector3>
      <X>-786.995361</X>
      <Y>720.000732</Y>
      <Z>339.809235</Z>
    </Vector3>
    <Vector3>
      <X>-632.591431</X>
      <Y>880.964</Y>
      <Z>339.807159</Z>
    </Vector3>
    <Vector3>
      <X>-549.3373</X>
      <Y>967.4386</Y>
      <Z>339.804</Z>
    </Vector3>
    <Vector3>
      <X>-480.2424</X>
      <Y>1020.55646</Y>
      <Z>339.7976</Z>
    </Vector3>
    <Vector3>
      <X>-464.105347</X>
      <Y>1076.29517</Y>
      <Z>339.828583</Z>
    </Vector3>
    <Vector3>
      <X>-390.525024</X>
      <Y>1120.195</Y>
      <Z>339.801971</Z>
    </Vector3>
    <Vector3>
      <X>-321.2465</X>
      <Y>1179.60889</Y>
      <Z>339.800446</Z>
    </Vector3>
    <Vector3>
      <X>-378.1716</X>
      <Y>1209.05591</Y>
      <Z>339.8006</Z>
    </Vector3>
    <Vector3>
      <X>-697.938049</X>
      <Y>1010.65527</Y>
      <Z>366.513855</Z>
    </Vector3>
    <Vector3>
      <X>-804.349731</X>
      <Y>935.6816</Y>
      <Z>366.492554</Z>
    </Vector3>
    <Vector3>
      <X>-724.175354</X>
      <Y>881.107239</Y>
      <Z>366.466248</Z>
    </Vector3>
    <Vector3>
      <X>-557.8631</X>
      <Y>976.833435</Y>
      <Z>366.474152</Z>
    </Vector3>
    <Vector3>
      <X>-558.493958</X>
      <Y>1064.88489</Y>
      <Z>366.479858</Z>
    </Vector3>
    <Vector3>
      <X>-643.4215</X>
      <Y>1120.89038</Y>
      <Z>366.478516</Z>
    </Vector3>
    <Vector3>
      <X>-634.9086</X>
      <Y>1178.5542</Y>
      <Z>366.478455</Z>
    </Vector3>
    <Vector3>
      <X>-516.9827</X>
      <Y>1101.184</Y>
      <Z>366.476257</Z>
    </Vector3>
  </Checkpoints>
  <SpawnPoints>
    <SpawnPoint>
      <Position>
        <X>-520.9863</X>
        <Y>1110.69788</Y>
        <Z>366.723236</Z>
      </Position>
      <Heading>-143.202438</Heading>
    </SpawnPoint>
    <SpawnPoint>
      <Position>
        <X>-530.0274</X>
        <Y>1110.4314</Y>
        <Z>366.723267</Z>
      </Position>
      <Heading>-133.4466</Heading>
    </SpawnPoint>
    <SpawnPoint>
      <Position>
        <X>-529.3612</X>
        <Y>1119.38623</Y>
        <Z>366.723267</Z>
      </Position>
      <Heading>-138.006821</Heading>
    </SpawnPoint>
    <SpawnPoint>
      <Position>
        <X>-538.1795</X>
        <Y>1118.60742</Y>
        <Z>366.7235</Z>
      </Position>
      <Heading>-137.105225</Heading>
    </SpawnPoint>
    <SpawnPoint>
      <Position>
        <X>-537.4895</X>
        <Y>1127.50708</Y>
        <Z>366.723724</Z>
      </Position>
      <Heading>-139.161621</Heading>
    </SpawnPoint>
    <SpawnPoint>
      <Position>
        <X>-546.690857</X>
        <Y>1126.92236</Y>
        <Z>366.7235</Z>
      </Position>
      <Heading>-136.4803</Heading>
    </SpawnPoint>
    <SpawnPoint>
      <Position>
        <X>-545.8478</X>
        <Y>1136.02747</Y>
        <Z>366.7237</Z>
      </Position>
      <Heading>-139.574661</Heading>
    </SpawnPoint>
    <SpawnPoint>
      <Position>
        <X>-554.8853</X>
        <Y>1135.32312</Y>
        <Z>366.7237</Z>
      </Position>
      <Heading>-136.378876</Heading>
    </SpawnPoint>
    <SpawnPoint>
      <Position>
        <X>-553.9778</X>
        <Y>1144.14709</Y>
        <Z>366.723724</Z>
      </Position>
      <Heading>-140.0335</Heading>
    </SpawnPoint>
    <SpawnPoint>
      <Position>
        <X>-563.1346</X>
        <Y>1143.62317</Y>
        <Z>366.723724</Z>
      </Position>
      <Heading>-138.2262</Heading>
    </SpawnPoint>
    <SpawnPoint>
      <Position>
        <X>-562.426758</X>
        <Y>1152.59814</Y>
        <Z>366.7235</Z>
      </Position>
      <Heading>-142.52475</Heading>
    </SpawnPoint>
    <SpawnPoint>
      <Position>
        <X>-571.4415</X>
        <Y>1151.97571</Y>
        <Z>366.723236</Z>
      </Position>
      <Heading>-135.250885</Heading>
    </SpawnPoint>
    <SpawnPoint>
      <Position>
        <X>-570.718933</X>
        <Y>1160.7887</Y>
        <Z>366.723236</Z>
      </Position>
      <Heading>-140.60791</Heading>
    </SpawnPoint>
    <SpawnPoint>
      <Position>
        <X>-579.814453</X>
        <Y>1160.47388</Y>
        <Z>366.723236</Z>
      </Position>
      <Heading>-136.73996</Heading>
    </SpawnPoint>
    <SpawnPoint>
      <Position>
        <X>-578.886169</X>
        <Y>1169.20447</Y>
        <Z>366.723236</Z>
      </Position>
      <Heading>-137.492813</Heading>
    </SpawnPoint>
    <SpawnPoint>
      <Position>
        <X>-587.892944</X>
        <Y>1168.7804</Y>
        <Z>366.7237</Z>
      </Position>
      <Heading>-138.543625</Heading>
    </SpawnPoint>
  </SpawnPoints>
  <AvailableVehicles>
    <VehicleHash>Blazer5</VehicleHash>
  </AvailableVehicles>
  <LapsAvailable>true</LapsAvailable>
  <DecorativeProps>
    <SavedProp>
      <Position>
        <X>-395.929</X>
        <Y>979.398</Y>
        <Z>300.023</Z>
      </Position>
      <Rotation>
        <X>8.537736E-07</X>
        <Y>30.0499954</Y>
        <Z>-45.3999939</Z>
      </Rotation>
      <Hash>-780495775</Hash>
      <Dynamic>false</Dynamic>
      <Texture>9</Texture>
    </SavedProp>
    <SavedProp>
      <Position>
        <X>-148.088</X>
        <Y>746.113</Y>
        <Z>196.265</Z>
      </Position>
      <Rotation>
        <X>0</X>
        <Y>-0</Y>
        <Z>135.8</Z>
      </Rotation>
      <Hash>2138176025</Hash>
      <Dynamic>false</Dynamic>
      <Texture>2</Texture>
    </SavedProp>
    <SavedProp>
      <Position>
        <X>4.838</X>
        <Y>660.413</Y>
        <Z>195.756</Z>
      </Position>
      <Rotation>
        <X>0</X>
        <Y>0</Y>
        <Z>-36.8</Z>
      </Rotation>
      <Hash>-779638860</Hash>
      <Dynamic>false</Dynamic>
      <Texture>2</Texture>
    </SavedProp>
    <SavedProp>
      <Position>
        <X>-197.95</X>
        <Y>1311.196</Y>
        <Z>303.167</Z>
      </Position>
      <Rotation>
        <X>-4.241</X>
        <Y>3.86099982</Y>
        <Z>-12.6569977</Z>
      </Rotation>
      <Hash>398044554</Hash>
      <Dynamic>false</Dynamic>
      <Texture>1</Texture>
    </SavedProp>
    <SavedProp>
      <Position>
        <X>-210.884</X>
        <Y>1311.206</Y>
        <Z>303.993</Z>
      </Position>
      <Rotation>
        <X>-9.836</X>
        <Y>1.731</Y>
        <Z>14.348999</Z>
      </Rotation>
      <Hash>398044554</Hash>
      <Dynamic>false</Dynamic>
      <Texture>1</Texture>
    </SavedProp>
    <SavedProp>
      <Position>
        <X>-166.645</X>
        <Y>1280.747</Y>
        <Z>301.078</Z>
      </Position>
      <Rotation>
        <X>7.49200058</X>
        <Y>4.23800039</Y>
        <Z>-58.477993</Z>
      </Rotation>
      <Hash>398044554</Hash>
      <Dynamic>false</Dynamic>
      <Texture>1</Texture>
    </SavedProp>
    <SavedProp>
      <Position>
        <X>-175.831</X>
        <Y>1291.731</Y>
        <Z>302.323</Z>
      </Position>
      <Rotation>
        <X>-5.1069994</X>
        <Y>2.60699964</Y>
        <Z>-44.2839928</Z>
      </Rotation>
      <Hash>398044554</Hash>
      <Dynamic>false</Dynamic>
      <Texture>1</Texture>
    </SavedProp>
    <SavedProp>
      <Position>
        <X>-369.431</X>
        <Y>952.556</Y>
        <Z>276.295</Z>
      </Position>
      <Rotation>
        <X>-80.8000259</X>
        <Y>-0</Y>
        <Z>-135.002991</Z>
      </Rotation>
      <Hash>169991796</Hash>
      <Dynamic>false</Dynamic>
      <Texture>9</Texture>
    </SavedProp>
    <SavedProp>
      <Position>
        <X>-456.262</X>
        <Y>1087.62</Y>
        <Z>339.705</Z>
      </Position>
      <Rotation>
        <X>0</X>
        <Y>-0</Y>
        <Z>-163.699982</Z>
      </Rotation>
      <Hash>370845653</Hash>
      <Dynamic>false</Dynamic>
      <Texture>9</Texture>
    </SavedProp>
    <SavedProp>
      <Position>
        <X>-274.965</X>
        <Y>1033.05</Y>
        <Z>277.588</Z>
      </Position>
      <Rotation>
        <X>6.40400028</X>
        <Y>3.71500063</Y>
        <Z>-165.210983</Z>
      </Rotation>
      <Hash>2138176025</Hash>
      <Dynamic>false</Dynamic>
      <Texture>9</Texture>
    </SavedProp>
    <SavedProp>
      <Position>
        <X>-182.42</X>
        <Y>1063.09</Y>
        <Z>273.309</Z>
      </Position>
      <Rotation>
        <X>-54.5149956</X>
        <Y>-173.630981</Y>
        <Z>-159.60199</Z>
      </Rotation>
      <Hash>2138176025</Hash>
      <Dynamic>false</Dynamic>
      <Texture>9</Texture>
    </SavedProp>
    <SavedProp>
      <Position>
        <X>-113.338</X>
        <Y>1063.742</Y>
        <Z>204.819</Z>
      </Position>
      <Rotation>
        <X>0</X>
        <Y>-0</Y>
        <Z>-96.20099</Z>
      </Rotation>
      <Hash>-1705229539</Hash>
      <Dynamic>false</Dynamic>
      <Texture>9</Texture>
    </SavedProp>
    <SavedProp>
      <Position>
        <X>-68.601</X>
        <Y>1058.891</Y>
        <Z>201.381</Z>
      </Position>
      <Rotation>
        <X>0</X>
        <Y>0</Y>
        <Z>83.798996</Z>
      </Rotation>
      <Hash>167558631</Hash>
      <Dynamic>false</Dynamic>
      <Texture>9</Texture>
    </SavedProp>
    <SavedProp>
      <Position>
        <X>-38.776</X>
        <Y>1055.65</Y>
        <Z>201.391</Z>
      </Position>
      <Rotation>
        <X>0</X>
        <Y>0</Y>
        <Z>83.798996</Z>
      </Rotation>
      <Hash>167558631</Hash>
      <Dynamic>false</Dynamic>
      <Texture>9</Texture>
    </SavedProp>
    <SavedProp>
      <Position>
        <X>-14.497</X>
        <Y>1051.334</Y>
        <Z>201.401</Z>
      </Position>
      <Rotation>
        <X>0</X>
        <Y>0</Y>
        <Z>53.798996</Z>
      </Rotation>
      <Hash>702363064</Hash>
      <Dynamic>false</Dynamic>
      <Texture>9</Texture>
    </SavedProp>
    <SavedProp>
      <Position>
        <X>4.009</X>
        <Y>1038.654</Y>
        <Z>201.411</Z>
      </Position>
      <Rotation>
        <X>0</X>
        <Y>0</Y>
        <Z>23.799</Z>
      </Rotation>
      <Hash>702363064</Hash>
      <Dynamic>false</Dynamic>
      <Texture>9</Texture>
    </SavedProp>
    <SavedProp>
      <Position>
        <X>59.124</X>
        <Y>919.332</Y>
        <Z>195.773</Z>
      </Position>
      <Rotation>
        <X>-2.03555488E-13</X>
        <Y>179.999985</Y>
        <Z>-67.8009949</Z>
      </Rotation>
      <Hash>-212594584</Hash>
      <Dynamic>false</Dynamic>
      <Texture>2</Texture>
    </SavedProp>
    <SavedProp>
      <Position>
        <X>17.399</X>
        <Y>1014.154</Y>
        <Z>201.421</Z>
      </Position>
      <Rotation>
        <X>0</X>
        <Y>0</Y>
        <Z>23.799</Z>
      </Rotation>
      <Hash>167558631</Hash>
      <Dynamic>false</Dynamic>
      <Texture>9</Texture>
    </SavedProp>
    <SavedProp>
      <Position>
        <X>47.669</X>
        <Y>945.535</Y>
        <Z>199.013</Z>
      </Position>
      <Rotation>
        <X>0</X>
        <Y>0</Y>
        <Z>23.799</Z>
      </Rotation>
      <Hash>-982167178</Hash>
      <Dynamic>false</Dynamic>
      <Texture>2</Texture>
    </SavedProp>
    <SavedProp>
      <Position>
        <X>46.71</X>
        <Y>947.669</Y>
        <Z>224.302</Z>
      </Position>
      <Rotation>
        <X>8.537736E-07</X>
        <Y>-30.8</Y>
        <Z>113.599991</Z>
      </Rotation>
      <Hash>-66244843</Hash>
      <Dynamic>false</Dynamic>
      <Texture>9</Texture>
    </SavedProp>
    <SavedProp>
      <Position>
        <X>77.516</X>
        <Y>869.503</Y>
        <Z>194.74</Z>
      </Position>
      <Rotation>
        <X>0</X>
        <Y>0</Y>
        <Z>68.798996</Z>
      </Rotation>
      <Hash>138278167</Hash>
      <Dynamic>false</Dynamic>
      <Texture>2</Texture>
    </SavedProp>
    <SavedProp>
      <Position>
        <X>56.219</X>
        <Y>761.061</Y>
        <Z>194.75</Z>
      </Position>
      <Rotation>
        <X>0</X>
        <Y>-0</Y>
        <Z>-107.200989</Z>
      </Rotation>
      <Hash>1533556199</Hash>
      <Dynamic>false</Dynamic>
      <Texture>2</Texture>
    </SavedProp>
    <SavedProp>
      <Position>
        <X>-134.071</X>
        <Y>1065.926</Y>
        <Z>255.689</Z>
      </Position>
      <Rotation>
        <X>-1.067217E-07</X>
        <Y>-15.039999</Y>
        <Z>173.799</Z>
      </Rotation>
      <Hash>-66244843</Hash>
      <Dynamic>false</Dynamic>
      <Texture>9</Texture>
    </SavedProp>
    <SavedProp>
      <Position>
        <X>-96.195</X>
        <Y>711.2</Y>
        <Z>195.671</Z>
      </Position>
      <Rotation>
        <X>0</X>
        <Y>-0</Y>
        <Z>140.19899</Z>
      </Rotation>
      <Hash>-1591889033</Hash>
      <Dynamic>false</Dynamic>
      <Texture>1</Texture>
    </SavedProp>
    <SavedProp>
      <Position>
        <X>-73.038</X>
        <Y>685.133</Y>
        <Z>195.761</Z>
      </Position>
      <Rotation>
        <X>0</X>
        <Y>-0</Y>
        <Z>140.19899</Z>
      </Rotation>
      <Hash>-1591889033</Hash>
      <Dynamic>false</Dynamic>
      <Texture>1</Texture>
    </SavedProp>
    <SavedProp>
      <Position>
        <X>-40.981</X>
        <Y>673.691</Y>
        <Z>195.792</Z>
      </Position>
      <Rotation>
        <X>0</X>
        <Y>-0</Y>
        <Z>140.19899</Z>
      </Rotation>
      <Hash>-1591889033</Hash>
      <Dynamic>false</Dynamic>
      <Texture>1</Texture>
    </SavedProp>
    <SavedProp>
      <Position>
        <X>-343.828</X>
        <Y>978.157</Y>
        <Z>276.305</Z>
      </Position>
      <Rotation>
        <X>-80.8000259</X>
        <Y>-0</Y>
        <Z>-135.002991</Z>
      </Rotation>
      <Hash>-1170462683</Hash>
      <Dynamic>false</Dynamic>
      <Texture>9</Texture>
    </SavedProp>
    <SavedProp>
      <Position>
        <X>-330.599</X>
        <Y>991.384</Y>
        <Z>276.315</Z>
      </Position>
      <Rotation>
        <X>80.8000259</X>
        <Y>-0</Y>
        <Z>44.9969978</Z>
      </Rotation>
      <Hash>1125864094</Hash>
      <Dynamic>false</Dynamic>
      <Texture>9</Texture>
    </SavedProp>
    <SavedProp>
      <Position>
        <X>-317.37</X>
        <Y>1004.612</Y>
        <Z>276.325</Z>
      </Position>
      <Rotation>
        <X>80.8000259</X>
        <Y>-0</Y>
        <Z>44.9969978</Z>
      </Rotation>
      <Hash>1125864094</Hash>
      <Dynamic>false</Dynamic>
      <Texture>9</Texture>
    </SavedProp>
    <SavedProp>
      <Position>
        <X>-460.363</X>
        <Y>1044.738</Y>
        <Z>353.1</Z>
      </Position>
      <Rotation>
        <X>8.537736E-07</X>
        <Y>30.0499954</Y>
        <Z>-45.3999939</Z>
      </Rotation>
      <Hash>-544198516</Hash>
      <Dynamic>false</Dynamic>
      <Texture>9</Texture>
    </SavedProp>
    <SavedProp>
      <Position>
        <X>-495.071</X>
        <Y>1079.861</Y>
        <Z>366.357</Z>
      </Position>
      <Rotation>
        <X>0</X>
        <Y>0</Y>
        <Z>-45.5</Z>
      </Rotation>
      <Hash>-544198516</Hash>
      <Dynamic>false</Dynamic>
      <Texture>9</Texture>
    </SavedProp>
    <SavedProp>
      <Position>
        <X>-550.844</X>
        <Y>1136.487</Y>
        <Z>366.414</Z>
      </Position>
      <Rotation>
        <X>0</X>
        <Y>-0</Y>
        <Z>134.6</Z>
      </Rotation>
      <Hash>368293996</Hash>
      <Dynamic>false</Dynamic>
      <Texture>9</Texture>
    </SavedProp>
    <SavedProp>
      <Position>
        <X>-409.009</X>
        <Y>1113.706</Y>
        <Z>339.692</Z>
      </Position>
      <Rotation>
        <X>0</X>
        <Y>0</Y>
        <Z>16.2999973</Z>
      </Rotation>
      <Hash>-544198516</Hash>
      <Dynamic>false</Dynamic>
      <Texture>9</Texture>
    </SavedProp>
    <SavedProp>
      <Position>
        <X>-359.275</X>
        <Y>1131.432</Y>
        <Z>339.737</Z>
      </Position>
      <Rotation>
        <X>0</X>
        <Y>0</Y>
        <Z>16.2999973</Z>
      </Rotation>
      <Hash>2115578108</Hash>
      <Dynamic>false</Dynamic>
      <Texture>9</Texture>
    </SavedProp>
    <SavedProp>
      <Position>
        <X>-336.626</X>
        <Y>1187.62</Y>
        <Z>339.736</Z>
      </Position>
      <Rotation>
        <X>0</X>
        <Y>0</Y>
        <Z>31.2999954</Z>
      </Rotation>
      <Hash>-1970950312</Hash>
      <Dynamic>false</Dynamic>
      <Texture>9</Texture>
    </SavedProp>
    <SavedProp>
      <Position>
        <X>-446.375</X>
        <Y>1166.43</Y>
        <Z>339.69</Z>
      </Position>
      <Rotation>
        <X>0</X>
        <Y>-0</Y>
        <Z>-148.699982</Z>
      </Rotation>
      <Hash>-2065716143</Hash>
      <Dynamic>false</Dynamic>
      <Texture>9</Texture>
    </SavedProp>
    <SavedProp>
      <Position>
        <X>-387.847</X>
        <Y>1201.984</Y>
        <Z>339.834</Z>
      </Position>
      <Rotation>
        <X>-5.336085E-08</X>
        <Y>-1.954</Y>
        <Z>-149.000992</Z>
      </Rotation>
      <Hash>-388593496</Hash>
      <Dynamic>false</Dynamic>
      <Texture>9</Texture>
    </SavedProp>
    <SavedProp>
      <Position>
        <X>-501.035522</X>
        <Y>1133.23108</Y>
        <Z>376.065</Z>
      </Position>
      <Rotation>
        <X>0.0009989151</X>
        <Y>-28.4000015</Y>
        <Z>-148.478989</Z>
      </Rotation>
      <Hash>-388593496</Hash>
      <Dynamic>false</Dynamic>
      <Texture>9</Texture>
    </SavedProp>
    <SavedProp>
      <Position>
        <X>-633.5</X>
        <Y>1164.895</Y>
        <Z>366.414</Z>
      </Position>
      <Rotation>
        <X>0</X>
        <Y>-0</Y>
        <Z>134.6</Z>
      </Rotation>
      <Hash>-1970950312</Hash>
      <Dynamic>false</Dynamic>
      <Texture>9</Texture>
    </SavedProp>
    <SavedProp>
      <Position>
        <X>-621.978</X>
        <Y>1105.223</Y>
        <Z>366.415</Z>
      </Position>
      <Rotation>
        <X>0</X>
        <Y>0</Y>
        <Z>-45.3999977</Z>
      </Rotation>
      <Hash>1682688844</Hash>
      <Dynamic>false</Dynamic>
      <Texture>9</Texture>
    </SavedProp>
    <SavedProp>
      <Position>
        <X>-584.996</X>
        <Y>1087.045</Y>
        <Z>366.416</Z>
      </Position>
      <Rotation>
        <X>0</X>
        <Y>-0</Y>
        <Z>134.6</Z>
      </Rotation>
      <Hash>1682688844</Hash>
      <Dynamic>false</Dynamic>
      <Texture>9</Texture>
    </SavedProp>
    <SavedProp>
      <Position>
        <X>-549.063</X>
        <Y>1054.243</Y>
        <Z>366.416</Z>
      </Position>
      <Rotation>
        <X>0</X>
        <Y>-0</Y>
        <Z>119.599991</Z>
      </Rotation>
      <Hash>2115578108</Hash>
      <Dynamic>false</Dynamic>
      <Texture>9</Texture>
    </SavedProp>
    <SavedProp>
      <Position>
        <X>-532.529</X>
        <Y>1005.199</Y>
        <Z>366.399</Z>
      </Position>
      <Rotation>
        <X>0</X>
        <Y>0</Y>
        <Z>29.5999985</Z>
      </Rotation>
      <Hash>-2143953919</Hash>
      <Dynamic>false</Dynamic>
      <Texture>9</Texture>
    </SavedProp>
    <SavedProp>
      <Position>
        <X>-685.825</X>
        <Y>903.275</Y>
        <Z>366.418</Z>
      </Position>
      <Rotation>
        <X>0</X>
        <Y>0</Y>
        <Z>29.5999985</Z>
      </Rotation>
      <Hash>711357200</Hash>
      <Dynamic>false</Dynamic>
      <Texture>9</Texture>
    </SavedProp>
    <SavedProp>
      <Position>
        <X>-593.641</X>
        <Y>955.643</Y>
        <Z>366.417</Z>
      </Position>
      <Rotation>
        <X>0</X>
        <Y>0</Y>
        <Z>29.5999985</Z>
      </Rotation>
      <Hash>654660724</Hash>
      <Dynamic>false</Dynamic>
      <Texture>9</Texture>
    </SavedProp>
    <SavedProp>
      <Position>
        <X>-441.971</X>
        <Y>1169.104</Y>
        <Z>348.909</Z>
      </Position>
      <Rotation>
        <X>-4.268868E-07</X>
        <Y>-14.205</Y>
        <Z>-148.901</Z>
      </Rotation>
      <Hash>-388593496</Hash>
      <Dynamic>false</Dynamic>
      <Texture>9</Texture>
    </SavedProp>
    <SavedProp>
      <Position>
        <X>-299.262</X>
        <Y>881.402</Y>
        <Z>220.388</Z>
      </Position>
      <Rotation>
        <X>8.537736E-07</X>
        <Y>-30.05</Y>
        <Z>134.6</Z>
      </Rotation>
      <Hash>-780495775</Hash>
      <Dynamic>false</Dynamic>
      <Texture>9</Texture>
    </SavedProp>
    <SavedProp>
      <Position>
        <X>-759.684</X>
        <Y>876.155</Y>
        <Z>366.402</Z>
      </Position>
      <Rotation>
        <X>0</X>
        <Y>0</Y>
        <Z>-60.3999939</Z>
      </Rotation>
      <Hash>-2143953919</Hash>
      <Dynamic>false</Dynamic>
      <Texture>9</Texture>
    </SavedProp>
    <SavedProp>
      <Position>
        <X>-787.421</X>
        <Y>898.858</Y>
        <Z>366.42</Z>
      </Position>
      <Rotation>
        <X>0</X>
        <Y>0</Y>
        <Z>-60.3999939</Z>
      </Rotation>
      <Hash>-1383314327</Hash>
      <Dynamic>false</Dynamic>
      <Texture>9</Texture>
    </SavedProp>
    <SavedProp>
      <Position>
        <X>-796.149</X>
        <Y>914.221</Y>
        <Z>366.42</Z>
      </Position>
      <Rotation>
        <X>0</X>
        <Y>0</Y>
        <Z>-60.3999939</Z>
      </Rotation>
      <Hash>-1383314327</Hash>
      <Dynamic>false</Dynamic>
      <Texture>9</Texture>
    </SavedProp>
    <SavedProp>
      <Position>
        <X>-801.449</X>
        <Y>949.67</Y>
        <Z>366.423</Z>
      </Position>
      <Rotation>
        <X>0</X>
        <Y>-0</Y>
        <Z>-150.399979</Z>
      </Rotation>
      <Hash>-2143953919</Hash>
      <Dynamic>false</Dynamic>
      <Texture>9</Texture>
    </SavedProp>
    <SavedProp>
      <Position>
        <X>-764.874</X>
        <Y>982.222</Y>
        <Z>366.44</Z>
      </Position>
      <Rotation>
        <X>0</X>
        <Y>-0</Y>
        <Z>-165.4</Z>
      </Rotation>
      <Hash>2115578108</Hash>
      <Dynamic>false</Dynamic>
      <Texture>9</Texture>
    </SavedProp>
    <SavedProp>
      <Position>
        <X>-715.695</X>
        <Y>1001.343</Y>
        <Z>366.45</Z>
      </Position>
      <Rotation>
        <X>0</X>
        <Y>0</Y>
        <Z>14.5999985</Z>
      </Rotation>
      <Hash>-439356460</Hash>
      <Dynamic>false</Dynamic>
      <Texture>9</Texture>
    </SavedProp>
    <SavedProp>
      <Position>
        <X>-395.034</X>
        <Y>926.955</Y>
        <Z>276.306</Z>
      </Position>
      <Rotation>
        <X>-80.8000259</X>
        <Y>-0</Y>
        <Z>-135.002991</Z>
      </Rotation>
      <Hash>-1170462683</Hash>
      <Dynamic>false</Dynamic>
      <Texture>9</Texture>
    </SavedProp>
    <SavedProp>
      <Position>
        <X>-431.946</X>
        <Y>889.605</Y>
        <Z>286.257</Z>
      </Position>
      <Rotation>
        <X>59.95101</X>
        <Y>93.59699</Y>
        <Z>-48.11699</Z>
      </Rotation>
      <Hash>2138176025</Hash>
      <Dynamic>false</Dynamic>
      <Texture>9</Texture>
    </SavedProp>
    <SavedProp>
      <Position>
        <X>-470.876</X>
        <Y>849.834</Y>
        <Z>305.283</Z>
      </Position>
      <Rotation>
        <X>-59.951004</X>
        <Y>-93.59699</Y>
        <Z>131.88298</Z>
      </Rotation>
      <Hash>-1170462683</Hash>
      <Dynamic>false</Dynamic>
      <Texture>9</Texture>
    </SavedProp>
    <SavedProp>
      <Position>
        <X>-500.925</X>
        <Y>818.398</Y>
        <Z>336.588</Z>
      </Position>
      <Rotation>
        <X>44.9720039</X>
        <Y>92.54499</Y>
        <Z>-46.8019943</Z>
      </Rotation>
      <Hash>1533556199</Hash>
      <Dynamic>false</Dynamic>
      <Texture>9</Texture>
    </SavedProp>
    <SavedProp>
      <Position>
        <X>-654.799</X>
        <Y>659.117</Y>
        <Z>339.653</Z>
      </Position>
      <Rotation>
        <X>-0.00799999852</X>
        <Y>0.021999998</Y>
        <Z>136.03598</Z>
      </Rotation>
      <Hash>1333144381</Hash>
      <Dynamic>false</Dynamic>
      <Texture>9</Texture>
    </SavedProp>
    <SavedProp>
      <Position>
        <X>-468.993</X>
        <Y>1033.775</Y>
        <Z>339.728</Z>
      </Position>
      <Rotation>
        <X>0</X>
        <Y>0</Y>
        <Z>16.2999973</Z>
      </Rotation>
      <Hash>-2143953919</Hash>
      <Dynamic>false</Dynamic>
      <Texture>9</Texture>
    </SavedProp>
    <SavedProp>
      <Position>
        <X>-511.817</X>
        <Y>1002.374</Y>
        <Z>339.745</Z>
      </Position>
      <Rotation>
        <X>0</X>
        <Y>-0</Y>
        <Z>-163.699982</Z>
      </Rotation>
      <Hash>1682688844</Hash>
      <Dynamic>false</Dynamic>
      <Texture>9</Texture>
    </SavedProp>
    <SavedProp>
      <Position>
        <X>-693.393</X>
        <Y>817.938</Y>
        <Z>339.706</Z>
      </Position>
      <Rotation>
        <X>0</X>
        <Y>0</Y>
        <Z>46.2999954</Z>
      </Rotation>
      <Hash>-780495775</Hash>
      <Dynamic>false</Dynamic>
      <Texture>9</Texture>
    </SavedProp>
    <SavedProp>
      <Position>
        <X>-784.952</X>
        <Y>722.125</Y>
        <Z>339.761</Z>
      </Position>
      <Rotation>
        <X>0</X>
        <Y>0</Y>
        <Z>46.2999954</Z>
      </Rotation>
      <Hash>711357200</Hash>
      <Dynamic>false</Dynamic>
      <Texture>9</Texture>
    </SavedProp>
    <SavedProp>
      <Position>
        <X>-828.704</X>
        <Y>633.24</Y>
        <Z>339.77</Z>
      </Position>
      <Rotation>
        <X>0</X>
        <Y>-0</Y>
        <Z>-133.7</Z>
      </Rotation>
      <Hash>-2019132063</Hash>
      <Dynamic>false</Dynamic>
      <Texture>9</Texture>
    </SavedProp>
    <SavedProp>
      <Position>
        <X>-768.729</X>
        <Y>575.927</Y>
        <Z>339.78</Z>
      </Position>
      <Rotation>
        <X>0</X>
        <Y>0</Y>
        <Z>-43.6999969</Z>
      </Rotation>
      <Hash>-2019132063</Hash>
      <Dynamic>false</Dynamic>
      <Texture>9</Texture>
    </SavedProp>
    <SavedProp>
      <Position>
        <X>-701.06</X>
        <Y>605.251</Y>
        <Z>339.791</Z>
      </Position>
      <Rotation>
        <X>0</X>
        <Y>0</Y>
        <Z>46.2999954</Z>
      </Rotation>
      <Hash>-948305930</Hash>
      <Dynamic>false</Dynamic>
      <Texture>9</Texture>
    </SavedProp>
    <SavedProp>
      <Position>
        <X>-667.564</X>
        <Y>643.647</Y>
        <Z>339.801</Z>
      </Position>
      <Rotation>
        <X>0</X>
        <Y>-0</Y>
        <Z>-133.7</Z>
      </Rotation>
      <Hash>1516660056</Hash>
      <Dynamic>false</Dynamic>
      <Texture>9</Texture>
    </SavedProp>
    <SavedProp>
      <Position>
        <X>-617.113</X>
        <Y>698.16</Y>
        <Z>348.434</Z>
      </Position>
      <Rotation>
        <X>12</X>
        <Y>4.36423619E-07</Y>
        <Z>-43.964</Z>
      </Rotation>
      <Hash>1333144381</Hash>
      <Dynamic>false</Dynamic>
      <Texture>9</Texture>
    </SavedProp>
    <SavedProp>
      <Position>
        <X>-701.282</X>
        <Y>1006.466</Y>
        <Z>366.298</Z>
      </Position>
      <Rotation>
        <X>0.006</X>
        <Y>-0</Y>
        <Z>-60.3999939</Z>
      </Rotation>
      <Hash>1333144381</Hash>
      <Dynamic>false</Dynamic>
      <Texture>9</Texture>
    </SavedProp>
    <SavedProp>
      <Position>
        <X>-641.914</X>
        <Y>1040.19</Y>
        <Z>372.864</Z>
      </Position>
      <Rotation>
        <X>10.000001</X>
        <Y>-0</Y>
        <Z>-60.3999939</Z>
      </Rotation>
      <Hash>1333144381</Hash>
      <Dynamic>false</Dynamic>
      <Texture>9</Texture>
    </SavedProp>
    <SavedProp>
      <Position>
        <X>-748.197</X>
        <Y>760.396</Y>
        <Z>339.806</Z>
      </Position>
      <Rotation>
        <X>0</X>
        <Y>0</Y>
        <Z>46.4</Z>
      </Rotation>
      <Hash>-1591889033</Hash>
      <Dynamic>false</Dynamic>
      <Texture>9</Texture>
    </SavedProp>
    <SavedProp>
      <Position>
        <X>-721.749</X>
        <Y>788.174</Y>
        <Z>339.819</Z>
      </Position>
      <Rotation>
        <X>0</X>
        <Y>0</Y>
        <Z>46.9999962</Z>
      </Rotation>
      <Hash>-1591889033</Hash>
      <Dynamic>false</Dynamic>
      <Texture>9</Texture>
    </SavedProp>
    <SavedProp>
      <Position>
        <X>-693.122</X>
        <Y>818.193</Y>
        <Z>339.815</Z>
      </Position>
      <Rotation>
        <X>0</X>
        <Y>0</Y>
        <Z>46.4</Z>
      </Rotation>
      <Hash>-1591889033</Hash>
      <Dynamic>false</Dynamic>
      <Texture>9</Texture>
    </SavedProp>
    <SavedProp>
      <Position>
        <X>-653.883</X>
        <Y>859.555</Y>
        <Z>316.335</Z>
      </Position>
      <Rotation>
        <X>0</X>
        <Y>-0</Y>
        <Z>136.099991</Z>
      </Rotation>
      <Hash>-227156169</Hash>
      <Dynamic>false</Dynamic>
      <Texture>9</Texture>
    </SavedProp>
    <SavedProp>
      <Position>
        <X>-601.833</X>
        <Y>913.751</Y>
        <Z>339.75</Z>
      </Position>
      <Rotation>
        <X>0</X>
        <Y>0</Y>
        <Z>46.2999954</Z>
      </Rotation>
      <Hash>654660724</Hash>
      <Dynamic>false</Dynamic>
      <Texture>9</Texture>
    </SavedProp>
    <SavedProp>
      <Position>
        <X>-546.897</X>
        <Y>971.239</Y>
        <Z>339.694</Z>
      </Position>
      <Rotation>
        <X>0</X>
        <Y>0</Y>
        <Z>46.2999954</Z>
      </Rotation>
      <Hash>-544198516</Hash>
      <Dynamic>false</Dynamic>
      <Texture>9</Texture>
    </SavedProp>
    <SavedProp>
      <Position>
        <X>-480.492</X>
        <Y>1065.222</Y>
        <Z>366.507</Z>
      </Position>
      <Rotation>
        <X>0</X>
        <Y>-0</Y>
        <Z>134.6</Z>
      </Rotation>
      <Hash>1431235846</Hash>
      <Dynamic>false</Dynamic>
      <Texture>9</Texture>
    </SavedProp>
    <SavedProp>
      <Position>
        <X>-186.925</X>
        <Y>780.735</Y>
        <Z>194.256</Z>
      </Position>
      <Rotation>
        <X>0</X>
        <Y>0</Y>
        <Z>-83.3999939</Z>
      </Rotation>
      <Hash>-1203351544</Hash>
      <Dynamic>false</Dynamic>
      <Texture>9</Texture>
    </SavedProp>
    <SavedProp>
      <Position>
        <X>-187.145</X>
        <Y>783.202</Y>
        <Z>194.24</Z>
      </Position>
      <Rotation>
        <X>0</X>
        <Y>0</Y>
        <Z>-83.3999939</Z>
      </Rotation>
      <Hash>-1203351544</Hash>
      <Dynamic>false</Dynamic>
      <Texture>9</Texture>
    </SavedProp>
    <SavedProp>
      <Position>
        <X>-187.226</X>
        <Y>781.986</Y>
        <Z>196.25</Z>
      </Position>
      <Rotation>
        <X>0</X>
        <Y>0</Y>
        <Z>-83.801</Z>
      </Rotation>
      <Hash>-365778495</Hash>
      <Dynamic>false</Dynamic>
      <Texture>1</Texture>
    </SavedProp>
    <SavedProp>
      <Position>
        <X>60.691</X>
        <Y>916.095</Y>
        <Z>204.318</Z>
      </Position>
      <Rotation>
        <X>0</X>
        <Y>-30.6999989</Y>
        <Z>113.598991</Z>
      </Rotation>
      <Hash>-66244843</Hash>
      <Dynamic>false</Dynamic>
      <Texture>9</Texture>
    </SavedProp>
    <SavedProp>
      <Position>
        <X>40.611</X>
        <Y>961.52</Y>
        <Z>160.855</Z>
      </Position>
      <Rotation>
        <X>59.95</X>
        <Y>179.999985</Y>
        <Z>-156.000992</Z>
      </Rotation>
      <Hash>158374374</Hash>
      <Dynamic>false</Dynamic>
      <Texture>2</Texture>
    </SavedProp>
    <SavedProp>
      <Position>
        <X>-588.645</X>
        <Y>727.681</Y>
        <Z>357.173</Z>
      </Position>
      <Rotation>
        <X>12.000001</X>
        <Y>-0</Y>
        <Z>-43.79999</Z>
      </Rotation>
      <Hash>1333144381</Hash>
      <Dynamic>false</Dynamic>
      <Texture>9</Texture>
    </SavedProp>
    <SavedProp>
      <Position>
        <X>-470.281</X>
        <Y>1066.982</Y>
        <Z>366.707</Z>
      </Position>
      <Rotation>
        <X>90</X>
        <Y>-135.599991</Y>
        <Z>0</Z>
      </Rotation>
      <Hash>670120870</Hash>
      <Dynamic>false</Dynamic>
      <Texture>9</Texture>
    </SavedProp>
    <SavedProp>
      <Position>
        <X>-482.43</X>
        <Y>1054.754</Y>
        <Z>366.755</Z>
      </Position>
      <Rotation>
        <X>-90</X>
        <Y>-44.3999977</Y>
        <Z>0</Z>
      </Rotation>
      <Hash>670120870</Hash>
      <Dynamic>false</Dynamic>
      <Texture>9</Texture>
    </SavedProp>
    <SavedProp>
      <Position>
        <X>-509.05</X>
        <Y>1112.259</Y>
        <Z>366.383</Z>
      </Position>
      <Rotation>
        <X>0</X>
        <Y>-0</Y>
        <Z>134.799</Z>
      </Rotation>
      <Hash>670120870</Hash>
      <Dynamic>false</Dynamic>
      <Texture>9</Texture>
    </SavedProp>
    <SavedProp>
      <Position>
        <X>-507.143</X>
        <Y>1110.324</Y>
        <Z>366.388</Z>
      </Position>
      <Rotation>
        <X>0</X>
        <Y>0</Y>
        <Z>-45.5009956</Z>
      </Rotation>
      <Hash>670120870</Hash>
      <Dynamic>false</Dynamic>
      <Texture>9</Texture>
    </SavedProp>
    <SavedProp>
      <Position>
        <X>-506.204</X>
        <Y>1113.138</Y>
        <Z>366.391</Z>
      </Position>
      <Rotation>
        <X>0</X>
        <Y>-0</Y>
        <Z>-137.001984</Z>
      </Rotation>
      <Hash>670120870</Hash>
      <Dynamic>false</Dynamic>
      <Texture>9</Texture>
    </SavedProp>
    <SavedProp>
      <Position>
        <X>-507.733</X>
        <Y>1111.631</Y>
        <Z>366.375</Z>
      </Position>
      <Rotation>
        <X>0</X>
        <Y>-0</Y>
        <Z>-135.001984</Z>
      </Rotation>
      <Hash>670120870</Hash>
      <Dynamic>false</Dynamic>
      <Texture>9</Texture>
    </SavedProp>
    <SavedProp>
      <Position>
        <X>-525.2</X>
        <Y>1095.865</Y>
        <Z>366.39</Z>
      </Position>
      <Rotation>
        <X>0</X>
        <Y>-0</Y>
        <Z>-135.812988</Z>
      </Rotation>
      <Hash>670120870</Hash>
      <Dynamic>false</Dynamic>
      <Texture>9</Texture>
    </SavedProp>
    <SavedProp>
      <Position>
        <X>-526.665</X>
        <Y>1092.901</Y>
        <Z>366.389</Z>
      </Position>
      <Rotation>
        <X>0</X>
        <Y>-0</Y>
        <Z>-135.002991</Z>
      </Rotation>
      <Hash>670120870</Hash>
      <Dynamic>false</Dynamic>
      <Texture>9</Texture>
    </SavedProp>
    <SavedProp>
      <Position>
        <X>-528.115</X>
        <Y>1091.452</Y>
        <Z>366.386</Z>
      </Position>
      <Rotation>
        <X>0</X>
        <Y>-0</Y>
        <Z>-135.002991</Z>
      </Rotation>
      <Hash>670120870</Hash>
      <Dynamic>false</Dynamic>
      <Texture>9</Texture>
    </SavedProp>
    <SavedProp>
      <Position>
        <X>21.778</X>
        <Y>979.213</Y>
        <Z>246.843</Z>
      </Position>
      <Rotation>
        <X>28.1089973</X>
        <Y>-11.0879984</Y>
        <Z>46.584</Z>
      </Rotation>
      <Hash>-365778495</Hash>
      <Dynamic>false</Dynamic>
      <Texture>1</Texture>
    </SavedProp>
    <SavedProp>
      <Position>
        <X>40.177</X>
        <Y>987.268</Y>
        <Z>246.771</Z>
      </Position>
      <Rotation>
        <X>27.3599987</X>
        <Y>12.9389992</Y>
        <Z>-2.562</Z>
      </Rotation>
      <Hash>-808444215</Hash>
      <Dynamic>false</Dynamic>
      <Texture>1</Texture>
    </SavedProp>
    <SavedProp>
      <Position>
        <X>-480.823578</X>
        <Y>839.5228</Y>
        <Z>314.033</Z>
      </Position>
      <Rotation>
        <X>4.09811328E-05</X>
        <Y>-146.893845</Y>
        <Z>46.6136246</Z>
      </Rotation>
      <Hash>-1170462683</Hash>
      <Dynamic>false</Dynamic>
      <Texture>0</Texture>
    </SavedProp>
    <SavedProp>
      <Position>
        <X>-490.29776</X>
        <Y>829.2308</Y>
        <Z>323.033</Z>
      </Position>
      <Rotation>
        <X>3.4150944E-05</X>
        <Y>-145.893127</Y>
        <Z>47.113308</Z>
      </Rotation>
      <Hash>-1170462683</Hash>
      <Dynamic>false</Dynamic>
      <Texture>0</Texture>
    </SavedProp>
    <SavedProp>
      <Position>
        <X>-535.711365</X>
        <Y>782.774048</Y>
        <Z>378.052246</Z>
      </Position>
      <Rotation>
        <X>0</X>
        <Y>0</Y>
        <Z>-40.9999123</Z>
      </Rotation>
      <Hash>737005456</Hash>
      <Dynamic>false</Dynamic>
      <Texture>0</Texture>
    </SavedProp>
    <SavedProp>
      <Position>
        <X>-534.6227</X>
        <Y>1112.66931</Y>
        <Z>402.663147</Z>
      </Position>
      <Rotation>
        <X>0</X>
        <Y>-0</Y>
        <Z>124.999519</Z>
      </Rotation>
      <Hash>737005456</Hash>
      <Dynamic>false</Dynamic>
      <Texture>0</Texture>
    </SavedProp>
    <SavedProp>
      <Position>
        <X>-454.585022</X>
        <Y>1162.01465</Y>
        <Z>352.409</Z>
      </Position>
      <Rotation>
        <X>-8.537736E-07</X>
        <Y>-14.205</Y>
        <Z>-148.901</Z>
      </Rotation>
      <Hash>-388593496</Hash>
      <Dynamic>false</Dynamic>
      <Texture>0</Texture>
    </SavedProp>
    <SavedProp>
      <Position>
        <X>-470.365662</X>
        <Y>1153.14539</Y>
        <Z>358.159</Z>
      </Position>
      <Rotation>
        <X>-8.537736E-07</X>
        <Y>-14.205</Y>
        <Z>-148.901</Z>
      </Rotation>
      <Hash>-388593496</Hash>
      <Dynamic>false</Dynamic>
      <Texture>0</Texture>
    </SavedProp>
    <SavedProp>
      <Position>
        <X>-489.195862</X>
        <Y>1141.93323</Y>
        <Z>366.909</Z>
      </Position>
      <Rotation>
        <X>-8.537736E-07</X>
        <Y>-14.205</Y>
        <Z>-148.901</Z>
      </Rotation>
      <Hash>-388593496</Hash>
      <Dynamic>false</Dynamic>
      <Texture>0</Texture>
    </SavedProp>
    <SavedProp>
      <Position>
        <X>-497.680176</X>
        <Y>1137.08826</Y>
        <Z>370.909</Z>
      </Position>
      <Rotation>
        <X>-8.537736E-07</X>
        <Y>-14.205</Y>
        <Z>-148.901</Z>
      </Rotation>
      <Hash>-388593496</Hash>
      <Dynamic>false</Dynamic>
      <Texture>0</Texture>
    </SavedProp>
    <SavedProp>
      <Position>
        <X>-497.680176</X>
        <Y>1137.08826</Y>
        <Z>370.909</Z>
      </Position>
      <Rotation>
        <X>-8.537736E-07</X>
        <Y>-14.205</Y>
        <Z>-148.901</Z>
      </Rotation>
      <Hash>-388593496</Hash>
      <Dynamic>false</Dynamic>
      <Texture>0</Texture>
    </SavedProp>
  </DecorativeProps>
  <Trigger>
    <X>-564.557556</X>
    <Y>1265.29858</Y>
    <Z>320.4941</Z>
  </Trigger>
  <Name>Water Slide</Name>
  <Description>It´s a race with the Blazer Aqua</Description>
</Race>